[
  {
    "斷層名稱": "新城斷層",
    "r": "<=1",
    "SDS": "0.88",
    "SD1": "0.52",
    "SMS": "1.2",
    "SM1": "0.74",
    "對應鄉鎮": "[新竹縣] 竹東鎮、關西鎮、新埔鎮、竹北市、橫山鄉、芎林鄉、寶山鄉、北埔鄉、峨眉鄉 [新竹市] 東區、北區、香山區 [苗栗縣] 竹南鎮、頭份市、三灣鄉"
  },
  {
    "斷層名稱": "新城斷層",
    "r": "3",
    "SDS": "0.84",
    "SD1": "0.5",
    "SMS": "1.1",
    "SM1": "0.66",
    "對應鄉鎮": "[新竹縣] 竹東鎮、關西鎮、新埔鎮、竹北市、橫山鄉、芎林鄉、寶山鄉、北埔鄉、峨眉鄉 [新竹市] 東區、北區、香山區 [苗栗縣] 竹南鎮、頭份市、三灣鄉"
  },
  {
    "斷層名稱": "新城斷層",
    "r": "5",
    "SDS": "0.81",
    "SD1": "0.47",
    "SMS": "1.05",
    "SM1": "0.61",
    "對應鄉鎮": "[新竹縣] 竹東鎮、關西鎮、新埔鎮、竹北市、橫山鄉、芎林鄉、寶山鄉、北埔鄉、峨眉鄉 [新竹市] 東區、北區、香山區 [苗栗縣] 竹南鎮、頭份市、三灣鄉"
  },
  {
    "斷層名稱": "新城斷層",
    "r": "7",
    "SDS": "0.8",
    "SD1": "0.45",
    "SMS": "1",
    "SM1": "0.55",
    "對應鄉鎮": "[新竹縣] 竹東鎮、關西鎮、新埔鎮、竹北市、橫山鄉、芎林鄉、寶山鄉、北埔鄉、峨眉鄉 [新竹市] 東區、北區、香山區 [苗栗縣] 竹南鎮、頭份市、三灣鄉"
  },
  {
    "斷層名稱": "新城斷層",
    "r": "9",
    "SDS": "0.8",
    "SD1": "0.45",
    "SMS": "1",
    "SM1": "0.55",
    "對應鄉鎮": "[新竹縣] 竹東鎮、關西鎮、新埔鎮、竹北市、橫山鄉、芎林鄉、寶山鄉、北埔鄉、峨眉鄉 [新竹市] 東區、北區、香山區 [苗栗縣] 竹南鎮、頭份市、三灣鄉"
  },
  {
    "斷層名稱": "新城斷層",
    "r": "11",
    "SDS": "0.8",
    "SD1": "0.45",
    "SMS": "1",
    "SM1": "0.55",
    "對應鄉鎮": "[新竹縣] 竹東鎮、關西鎮、新埔鎮、竹北市、橫山鄉、芎林鄉、寶山鄉、北埔鄉、峨眉鄉 [新竹市] 東區、北區、香山區 [苗栗縣] 竹南鎮、頭份市、三灣鄉"
  },
  {
    "斷層名稱": "新城斷層",
    "r": "13",
    "SDS": "0.8",
    "SD1": "0.45",
    "SMS": "1",
    "SM1": "0.55",
    "對應鄉鎮": "[新竹縣] 竹東鎮、關西鎮、新埔鎮、竹北市、橫山鄉、芎林鄉、寶山鄉、北埔鄉、峨眉鄉 [新竹市] 東區、北區、香山區 [苗栗縣] 竹南鎮、頭份市、三灣鄉"
  },
  {
    "斷層名稱": "新城斷層",
    "r": ">=14",
    "SDS": "0.8",
    "SD1": "0.45",
    "SMS": "1",
    "SM1": "0.55",
    "對應鄉鎮": "[新竹縣] 竹東鎮、關西鎮、新埔鎮、竹北市、橫山鄉、芎林鄉、寶山鄉、北埔鄉、峨眉鄉 [新竹市] 東區、北區、香山區 [苗栗縣] 竹南鎮、頭份市、三灣鄉"
  },
  {
    "斷層名稱": "新城斷層",
    "r": "<=1",
    "SDS": "0.88",
    "SD1": "0.52",
    "SMS": "1.2",
    "SM1": "0.74",
    "對應鄉鎮": "[桃園市] 龍潭區"
  },
  {
    "斷層名稱": "新城斷層",
    "r": "3",
    "SDS": "0.84",
    "SD1": "0.5",
    "SMS": "1.1",
    "SM1": "0.66",
    "對應鄉鎮": "[桃園市] 龍潭區"
  },
  {
    "斷層名稱": "新城斷層",
    "r": "5",
    "SDS": "0.81",
    "SD1": "0.47",
    "SMS": "1.05",
    "SM1": "0.61",
    "對應鄉鎮": "[桃園市] 龍潭區"
  },
  {
    "斷層名稱": "新城斷層",
    "r": "7",
    "SDS": "0.8",
    "SD1": "0.45",
    "SMS": "1",
    "SM1": "0.55",
    "對應鄉鎮": "[桃園市] 龍潭區"
  },
  {
    "斷層名稱": "新城斷層",
    "r": "9",
    "SDS": "0.7",
    "SD1": "0.4",
    "SMS": "0.9",
    "SM1": "0.5",
    "對應鄉鎮": "[桃園市] 龍潭區"
  },
  {
    "斷層名稱": "新城斷層",
    "r": "11",
    "SDS": "0.7",
    "SD1": "0.4",
    "SMS": "0.9",
    "SM1": "0.5",
    "對應鄉鎮": "[桃園市] 龍潭區"
  },
  {
    "斷層名稱": "新城斷層",
    "r": "13",
    "SDS": "0.7",
    "SD1": "0.4",
    "SMS": "0.9",
    "SM1": "0.5",
    "對應鄉鎮": "[桃園市] 龍潭區"
  },
  {
    "斷層名稱": "新城斷層",
    "r": ">=14",
    "SDS": "0.7",
    "SD1": "0.4",
    "SMS": "0.9",
    "SM1": "0.5",
    "對應鄉鎮": "[桃園市] 龍潭區"
  },
  {
    "斷層名稱": "獅潭斷層",
    "r": "<=1",
    "SDS": "1.02",
    "SD1": "0.6",
    "SMS": "1.26",
    "SM1": "0.78",
    "對應鄉鎮": "[新竹縣] 寶山鄉、北埔鄉、峨眉鄉 [苗栗縣] 公館鄉、銅鑼鄉、頭屋鄉、頭份市、造橋鄉、三灣鄉、南庄鄉、大湖鄉、獅潭鄉"
  },
  {
    "斷層名稱": "獅潭斷層",
    "r": "3",
    "SDS": "0.97",
    "SD1": "0.58",
    "SMS": "1.2",
    "SM1": "0.74",
    "對應鄉鎮": "[新竹縣] 寶山鄉、北埔鄉、峨眉鄉 [苗栗縣] 公館鄉、銅鑼鄉、頭屋鄉、頭份市、造橋鄉、三灣鄉、南庄鄉、大湖鄉、獅潭鄉"
  },
  {
    "斷層名稱": "獅潭斷層",
    "r": "5",
    "SDS": "0.93",
    "SD1": "0.54",
    "SMS": "1.13",
    "SM1": "0.69",
    "對應鄉鎮": "[新竹縣] 寶山鄉、北埔鄉、峨眉鄉 [苗栗縣] 公館鄉、銅鑼鄉、頭屋鄉、頭份市、造橋鄉、三灣鄉、南庄鄉、大湖鄉、獅潭鄉"
  },
  {
    "斷層名稱": "獅潭斷層",
    "r": "7",
    "SDS": "0.89",
    "SD1": "0.5",
    "SMS": "1.07",
    "SM1": "0.64",
    "對應鄉鎮": "[新竹縣] 寶山鄉、北埔鄉、峨眉鄉 [苗栗縣] 公館鄉、銅鑼鄉、頭屋鄉、頭份市、造橋鄉、三灣鄉、南庄鄉、大湖鄉、獅潭鄉"
  },
  {
    "斷層名稱": "獅潭斷層",
    "r": "9",
    "SDS": "0.85",
    "SD1": "0.48",
    "SMS": "1.03",
    "SM1": "0.6",
    "對應鄉鎮": "[新竹縣] 寶山鄉、北埔鄉、峨眉鄉 [苗栗縣] 公館鄉、銅鑼鄉、頭屋鄉、頭份市、造橋鄉、三灣鄉、南庄鄉、大湖鄉、獅潭鄉"
  },
  {
    "斷層名稱": "獅潭斷層",
    "r": "11",
    "SDS": "0.8",
    "SD1": "0.45",
    "SMS": "1",
    "SM1": "0.55",
    "對應鄉鎮": "[新竹縣] 寶山鄉、北埔鄉、峨眉鄉 [苗栗縣] 公館鄉、銅鑼鄉、頭屋鄉、頭份市、造橋鄉、三灣鄉、南庄鄉、大湖鄉、獅潭鄉"
  },
  {
    "斷層名稱": "獅潭斷層",
    "r": "13",
    "SDS": "0.8",
    "SD1": "0.45",
    "SMS": "1",
    "SM1": "0.55",
    "對應鄉鎮": "[新竹縣] 寶山鄉、北埔鄉、峨眉鄉 [苗栗縣] 公館鄉、銅鑼鄉、頭屋鄉、頭份市、造橋鄉、三灣鄉、南庄鄉、大湖鄉、獅潭鄉"
  },
  {
    "斷層名稱": "獅潭斷層",
    "r": ">=14",
    "SDS": "0.8",
    "SD1": "0.45",
    "SMS": "1",
    "SM1": "0.55",
    "對應鄉鎮": "[新竹縣] 寶山鄉、北埔鄉、峨眉鄉 [苗栗縣] 公館鄉、銅鑼鄉、頭屋鄉、頭份市、造橋鄉、三灣鄉、南庄鄉、大湖鄉、獅潭鄉"
  },
  {
    "斷層名稱": "獅潭斷層",
    "r": "<=1",
    "SDS": "1.02",
    "SD1": "0.6",
    "SMS": "1.26",
    "SM1": "0.78",
    "對應鄉鎮": "[新竹縣] 五峰鄉 [苗栗縣] 苗栗市、泰安鄉"
  },
  {
    "斷層名稱": "獅潭斷層",
    "r": "3",
    "SDS": "0.97",
    "SD1": "0.58",
    "SMS": "1.2",
    "SM1": "0.74",
    "對應鄉鎮": "[新竹縣] 五峰鄉 [苗栗縣] 苗栗市、泰安鄉"
  },
  {
    "斷層名稱": "獅潭斷層",
    "r": "5",
    "SDS": "0.93",
    "SD1": "0.54",
    "SMS": "1.13",
    "SM1": "0.69",
    "對應鄉鎮": "[新竹縣] 五峰鄉 [苗栗縣] 苗栗市、泰安鄉"
  },
  {
    "斷層名稱": "獅潭斷層",
    "r": "7",
    "SDS": "0.89",
    "SD1": "0.5",
    "SMS": "1.07",
    "SM1": "0.64",
    "對應鄉鎮": "[新竹縣] 五峰鄉 [苗栗縣] 苗栗市、泰安鄉"
  },
  {
    "斷層名稱": "獅潭斷層",
    "r": "9",
    "SDS": "0.85",
    "SD1": "0.48",
    "SMS": "1.03",
    "SM1": "0.6",
    "對應鄉鎮": "[新竹縣] 五峰鄉 [苗栗縣] 苗栗市、泰安鄉"
  },
  {
    "斷層名稱": "獅潭斷層",
    "r": "11",
    "SDS": "0.7",
    "SD1": "0.4",
    "SMS": "0.9",
    "SM1": "0.5",
    "對應鄉鎮": "[新竹縣] 五峰鄉 [苗栗縣] 苗栗市、泰安鄉"
  },
  {
    "斷層名稱": "獅潭斷層",
    "r": "13",
    "SDS": "0.7",
    "SD1": "0.4",
    "SMS": "0.9",
    "SM1": "0.5",
    "對應鄉鎮": "[新竹縣] 五峰鄉 [苗栗縣] 苗栗市、泰安鄉"
  },
  {
    "斷層名稱": "獅潭斷層",
    "r": ">=14",
    "SDS": "0.7",
    "SD1": "0.4",
    "SMS": "0.9",
    "SM1": "0.5",
    "對應鄉鎮": "[新竹縣] 五峰鄉 [苗栗縣] 苗栗市、泰安鄉"
  },
  {
    "斷層名稱": "三義斷層",
    "r": "<=1",
    "SDS": "0.88",
    "SD1": "0.52",
    "SMS": "1.2",
    "SM1": "0.74",
    "對應鄉鎮": "[苗栗縣] 苑裡鎮、公館鄉、銅鑼鄉、三義鄉、大湖鄉、卓蘭鎮 [臺中市] 中區、東區、西區、北區、西屯區、北屯區、豐原區、東勢區、大甲區、后里區、神岡區、潭子區、大雅區、新社區、石岡區、外埔區、太平區"
  },
  {
    "斷層名稱": "三義斷層",
    "r": "3",
    "SDS": "0.84",
    "SD1": "0.5",
    "SMS": "1.1",
    "SM1": "0.66",
    "對應鄉鎮": "[苗栗縣] 苑裡鎮、公館鄉、銅鑼鄉、三義鄉、大湖鄉、卓蘭鎮 [臺中市] 中區、東區、西區、北區、西屯區、北屯區、豐原區、東勢區、大甲區、后里區、神岡區、潭子區、大雅區、新社區、石岡區、外埔區、太平區"
  },
  {
    "斷層名稱": "三義斷層",
    "r": "5",
    "SDS": "0.81",
    "SD1": "0.47",
    "SMS": "1.05",
    "SM1": "0.61",
    "對應鄉鎮": "[苗栗縣] 苑裡鎮、公館鄉、銅鑼鄉、三義鄉、大湖鄉、卓蘭鎮 [臺中市] 中區、東區、西區、北區、西屯區、北屯區、豐原區、東勢區、大甲區、后里區、神岡區、潭子區、大雅區、新社區、石岡區、外埔區、太平區"
  },
  {
    "斷層名稱": "三義斷層",
    "r": "7",
    "SDS": "0.8",
    "SD1": "0.45",
    "SMS": "1",
    "SM1": "0.55",
    "對應鄉鎮": "[苗栗縣] 苑裡鎮、公館鄉、銅鑼鄉、三義鄉、大湖鄉、卓蘭鎮 [臺中市] 中區、東區、西區、北區、西屯區、北屯區、豐原區、東勢區、大甲區、后里區、神岡區、潭子區、大雅區、新社區、石岡區、外埔區、太平區"
  },
  {
    "斷層名稱": "三義斷層",
    "r": "9",
    "SDS": "0.8",
    "SD1": "0.45",
    "SMS": "1",
    "SM1": "0.55",
    "對應鄉鎮": "[苗栗縣] 苑裡鎮、公館鄉、銅鑼鄉、三義鄉、大湖鄉、卓蘭鎮 [臺中市] 中區、東區、西區、北區、西屯區、北屯區、豐原區、東勢區、大甲區、后里區、神岡區、潭子區、大雅區、新社區、石岡區、外埔區、太平區"
  },
  {
    "斷層名稱": "三義斷層",
    "r": "11",
    "SDS": "0.8",
    "SD1": "0.45",
    "SMS": "1",
    "SM1": "0.55",
    "對應鄉鎮": "[苗栗縣] 苑裡鎮、公館鄉、銅鑼鄉、三義鄉、大湖鄉、卓蘭鎮 [臺中市] 中區、東區、西區、北區、西屯區、北屯區、豐原區、東勢區、大甲區、后里區、神岡區、潭子區、大雅區、新社區、石岡區、外埔區、太平區"
  },
  {
    "斷層名稱": "三義斷層",
    "r": "13",
    "SDS": "0.8",
    "SD1": "0.45",
    "SMS": "1",
    "SM1": "0.55",
    "對應鄉鎮": "[苗栗縣] 苑裡鎮、公館鄉、銅鑼鄉、三義鄉、大湖鄉、卓蘭鎮 [臺中市] 中區、東區、西區、北區、西屯區、北屯區、豐原區、東勢區、大甲區、后里區、神岡區、潭子區、大雅區、新社區、石岡區、外埔區、太平區"
  },
  {
    "斷層名稱": "三義斷層",
    "r": ">=14",
    "SDS": "0.8",
    "SD1": "0.45",
    "SMS": "1",
    "SM1": "0.55",
    "對應鄉鎮": "[苗栗縣] 苑裡鎮、公館鄉、銅鑼鄉、三義鄉、大湖鄉、卓蘭鎮 [臺中市] 中區、東區、西區、北區、西屯區、北屯區、豐原區、東勢區、大甲區、后里區、神岡區、潭子區、大雅區、新社區、石岡區、外埔區、太平區"
  },
  {
    "斷層名稱": "三義斷層",
    "r": "<=1",
    "SDS": "0.88",
    "SD1": "0.52",
    "SMS": "1.2",
    "SM1": "0.74",
    "對應鄉鎮": "[苗栗縣] 通霄鎮"
  },
  {
    "斷層名稱": "三義斷層",
    "r": "3",
    "SDS": "0.84",
    "SD1": "0.5",
    "SMS": "1.1",
    "SM1": "0.66",
    "對應鄉鎮": "[苗栗縣] 通霄鎮"
  },
  {
    "斷層名稱": "三義斷層",
    "r": "5",
    "SDS": "0.81",
    "SD1": "0.47",
    "SMS": "1.05",
    "SM1": "0.61",
    "對應鄉鎮": "[苗栗縣] 通霄鎮"
  },
  {
    "斷層名稱": "三義斷層",
    "r": "7",
    "SDS": "0.7",
    "SD1": "0.4",
    "SMS": "0.9",
    "SM1": "0.5",
    "對應鄉鎮": "[苗栗縣] 通霄鎮"
  },
  {
    "斷層名稱": "三義斷層",
    "r": "9",
    "SDS": "0.7",
    "SD1": "0.4",
    "SMS": "0.9",
    "SM1": "0.5",
    "對應鄉鎮": "[苗栗縣] 通霄鎮"
  },
  {
    "斷層名稱": "三義斷層",
    "r": "11",
    "SDS": "0.7",
    "SD1": "0.4",
    "SMS": "0.9",
    "SM1": "0.5",
    "對應鄉鎮": "[苗栗縣] 通霄鎮"
  },
  {
    "斷層名稱": "三義斷層",
    "r": "13",
    "SDS": "0.7",
    "SD1": "0.4",
    "SMS": "0.9",
    "SM1": "0.5",
    "對應鄉鎮": "[苗栗縣] 通霄鎮"
  },
  {
    "斷層名稱": "三義斷層",
    "r": ">=14",
    "SDS": "0.7",
    "SD1": "0.4",
    "SMS": "0.9",
    "SM1": "0.5",
    "對應鄉鎮": "[苗栗縣] 通霄鎮"
  },
  {
    "斷層名稱": "大甲斷層全段",
    "r": "<=1",
    "SDS": "1.08",
    "SD1": "0.63",
    "SMS": "1.33",
    "SM1": "0.83",
    "對應鄉鎮": "[苗栗縣] 苑裡鎮、三義鄉 [臺中市] 中區、西區、南區、北區、西屯區、北屯區、南屯區、豐原區、大甲區、后里區、清水區、沙鹿區、梧棲區、神岡區、潭子區、大雅區、外埔區、大安區、烏日區、大肚區、龍井區、霧峰區、大里區 [彰化縣] 彰化市、和美鎮、北斗鎮、員林市、田中鎮、線西鄉、伸港鄉、秀水鄉、花壇鄉、芬園鄉、大村鄉、埔心鄉、永靖鄉、社頭鄉、二水鄉、田尾鄉、溪州鄉 [南投縣] 南投市、草屯鎮、竹山鎮、名間鄉、中寮鄉 [雲林縣] 斗六市、莿桐鄉、林內鄉"
  },
  {
    "斷層名稱": "大甲斷層全段",
    "r": "3",
    "SDS": "1.02",
    "SD1": "0.58",
    "SMS": "1.21",
    "SM1": "0.75",
    "對應鄉鎮": "[苗栗縣] 苑裡鎮、三義鄉 [臺中市] 中區、西區、南區、北區、西屯區、北屯區、南屯區、豐原區、大甲區、后里區、清水區、沙鹿區、梧棲區、神岡區、潭子區、大雅區、外埔區、大安區、烏日區、大肚區、龍井區、霧峰區、大里區 [彰化縣] 彰化市、和美鎮、北斗鎮、員林市、田中鎮、線西鄉、伸港鄉、秀水鄉、花壇鄉、芬園鄉、大村鄉、埔心鄉、永靖鄉、社頭鄉、二水鄉、田尾鄉、溪州鄉 [南投縣] 南投市、草屯鎮、竹山鎮、名間鄉、中寮鄉 [雲林縣] 斗六市、莿桐鄉、林內鄉"
  },
  {
    "斷層名稱": "大甲斷層全段",
    "r": "5",
    "SDS": "0.94",
    "SD1": "0.53",
    "SMS": "1.14",
    "SM1": "0.69",
    "對應鄉鎮": "[苗栗縣] 苑裡鎮、三義鄉 [臺中市] 中區、西區、南區、北區、西屯區、北屯區、南屯區、豐原區、大甲區、后里區、清水區、沙鹿區、梧棲區、神岡區、潭子區、大雅區、外埔區、大安區、烏日區、大肚區、龍井區、霧峰區、大里區 [彰化縣] 彰化市、和美鎮、北斗鎮、員林市、田中鎮、線西鄉、伸港鄉、秀水鄉、花壇鄉、芬園鄉、大村鄉、埔心鄉、永靖鄉、社頭鄉、二水鄉、田尾鄉、溪州鄉 [南投縣] 南投市、草屯鎮、竹山鎮、名間鄉、中寮鄉 [雲林縣] 斗六市、莿桐鄉、林內鄉"
  },
  {
    "斷層名稱": "大甲斷層全段",
    "r": "7",
    "SDS": "0.87",
    "SD1": "0.49",
    "SMS": "1.09",
    "SM1": "0.65",
    "對應鄉鎮": "[苗栗縣] 苑裡鎮、三義鄉 [臺中市] 中區、西區、南區、北區、西屯區、北屯區、南屯區、豐原區、大甲區、后里區、清水區、沙鹿區、梧棲區、神岡區、潭子區、大雅區、外埔區、大安區、烏日區、大肚區、龍井區、霧峰區、大里區 [彰化縣] 彰化市、和美鎮、北斗鎮、員林市、田中鎮、線西鄉、伸港鄉、秀水鄉、花壇鄉、芬園鄉、大村鄉、埔心鄉、永靖鄉、社頭鄉、二水鄉、田尾鄉、溪州鄉 [南投縣] 南投市、草屯鎮、竹山鎮、名間鄉、中寮鄉 [雲林縣] 斗六市、莿桐鄉、林內鄉"
  },
  {
    "斷層名稱": "大甲斷層全段",
    "r": "9",
    "SDS": "0.85",
    "SD1": "0.48",
    "SMS": "1.06",
    "SM1": "0.62",
    "對應鄉鎮": "[苗栗縣] 苑裡鎮、三義鄉 [臺中市] 中區、西區、南區、北區、西屯區、北屯區、南屯區、豐原區、大甲區、后里區、清水區、沙鹿區、梧棲區、神岡區、潭子區、大雅區、外埔區、大安區、烏日區、大肚區、龍井區、霧峰區、大里區 [彰化縣] 彰化市、和美鎮、北斗鎮、員林市、田中鎮、線西鄉、伸港鄉、秀水鄉、花壇鄉、芬園鄉、大村鄉、埔心鄉、永靖鄉、社頭鄉、二水鄉、田尾鄉、溪州鄉 [南投縣] 南投市、草屯鎮、竹山鎮、名間鄉、中寮鄉 [雲林縣] 斗六市、莿桐鄉、林內鄉"
  },
  {
    "斷層名稱": "大甲斷層全段",
    "r": "11",
    "SDS": "0.83",
    "SD1": "0.46",
    "SMS": "1.03",
    "SM1": "0.59",
    "對應鄉鎮": "[苗栗縣] 苑裡鎮、三義鄉 [臺中市] 中區、西區、南區、北區、西屯區、北屯區、南屯區、豐原區、大甲區、后里區、清水區、沙鹿區、梧棲區、神岡區、潭子區、大雅區、外埔區、大安區、烏日區、大肚區、龍井區、霧峰區、大里區 [彰化縣] 彰化市、和美鎮、北斗鎮、員林市、田中鎮、線西鄉、伸港鄉、秀水鄉、花壇鄉、芬園鄉、大村鄉、埔心鄉、永靖鄉、社頭鄉、二水鄉、田尾鄉、溪州鄉 [南投縣] 南投市、草屯鎮、竹山鎮、名間鄉、中寮鄉 [雲林縣] 斗六市、莿桐鄉、林內鄉"
  },
  {
    "斷層名稱": "大甲斷層全段",
    "r": "13",
    "SDS": "0.8",
    "SD1": "0.45",
    "SMS": "1",
    "SM1": "0.55",
    "對應鄉鎮": "[苗栗縣] 苑裡鎮、三義鄉 [臺中市] 中區、西區、南區、北區、西屯區、北屯區、南屯區、豐原區、大甲區、后里區、清水區、沙鹿區、梧棲區、神岡區、潭子區、大雅區、外埔區、大安區、烏日區、大肚區、龍井區、霧峰區、大里區 [彰化縣] 彰化市、和美鎮、北斗鎮、員林市、田中鎮、線西鄉、伸港鄉、秀水鄉、花壇鄉、芬園鄉、大村鄉、埔心鄉、永靖鄉、社頭鄉、二水鄉、田尾鄉、溪州鄉 [南投縣] 南投市、草屯鎮、竹山鎮、名間鄉、中寮鄉 [雲林縣] 斗六市、莿桐鄉、林內鄉"
  },
  {
    "斷層名稱": "大甲斷層全段",
    "r": ">=14",
    "SDS": "0.8",
    "SD1": "0.45",
    "SMS": "1",
    "SM1": "0.55",
    "對應鄉鎮": "[苗栗縣] 苑裡鎮、三義鄉 [臺中市] 中區、西區、南區、北區、西屯區、北屯區、南屯區、豐原區、大甲區、后里區、清水區、沙鹿區、梧棲區、神岡區、潭子區、大雅區、外埔區、大安區、烏日區、大肚區、龍井區、霧峰區、大里區 [彰化縣] 彰化市、和美鎮、北斗鎮、員林市、田中鎮、線西鄉、伸港鄉、秀水鄉、花壇鄉、芬園鄉、大村鄉、埔心鄉、永靖鄉、社頭鄉、二水鄉、田尾鄉、溪州鄉 [南投縣] 南投市、草屯鎮、竹山鎮、名間鄉、中寮鄉 [雲林縣] 斗六市、莿桐鄉、林內鄉"
  },
  {
    "斷層名稱": "大甲斷層全段",
    "r": "<=1",
    "SDS": "1.08",
    "SD1": "0.63",
    "SMS": "1.33",
    "SM1": "0.83",
    "對應鄉鎮": "[苗栗縣] 通霄鎮 [彰化縣] 鹿港鎮、溪湖鎮、福興鄉、埔鹽鄉、埤頭鄉 [雲林縣] 西螺鎮"
  },
  {
    "斷層名稱": "大甲斷層全段",
    "r": "3",
    "SDS": "1.02",
    "SD1": "0.58",
    "SMS": "1.21",
    "SM1": "0.75",
    "對應鄉鎮": "[苗栗縣] 通霄鎮 [彰化縣] 鹿港鎮、溪湖鎮、福興鄉、埔鹽鄉、埤頭鄉 [雲林縣] 西螺鎮"
  },
  {
    "斷層名稱": "大甲斷層全段",
    "r": "5",
    "SDS": "0.94",
    "SD1": "0.53",
    "SMS": "1.14",
    "SM1": "0.69",
    "對應鄉鎮": "[苗栗縣] 通霄鎮 [彰化縣] 鹿港鎮、溪湖鎮、福興鄉、埔鹽鄉、埤頭鄉 [雲林縣] 西螺鎮"
  },
  {
    "斷層名稱": "大甲斷層全段",
    "r": "7",
    "SDS": "0.87",
    "SD1": "0.49",
    "SMS": "1.09",
    "SM1": "0.65",
    "對應鄉鎮": "[苗栗縣] 通霄鎮 [彰化縣] 鹿港鎮、溪湖鎮、福興鄉、埔鹽鄉、埤頭鄉 [雲林縣] 西螺鎮"
  },
  {
    "斷層名稱": "大甲斷層全段",
    "r": "9",
    "SDS": "0.85",
    "SD1": "0.48",
    "SMS": "1.06",
    "SM1": "0.62",
    "對應鄉鎮": "[苗栗縣] 通霄鎮 [彰化縣] 鹿港鎮、溪湖鎮、福興鄉、埔鹽鄉、埤頭鄉 [雲林縣] 西螺鎮"
  },
  {
    "斷層名稱": "大甲斷層全段",
    "r": "11",
    "SDS": "0.83",
    "SD1": "0.46",
    "SMS": "1.03",
    "SM1": "0.59",
    "對應鄉鎮": "[苗栗縣] 通霄鎮 [彰化縣] 鹿港鎮、溪湖鎮、福興鄉、埔鹽鄉、埤頭鄉 [雲林縣] 西螺鎮"
  },
  {
    "斷層名稱": "大甲斷層全段",
    "r": "13",
    "SDS": "0.8",
    "SD1": "0.45",
    "SMS": "1",
    "SM1": "0.55",
    "對應鄉鎮": "[苗栗縣] 通霄鎮 [彰化縣] 鹿港鎮、溪湖鎮、福興鄉、埔鹽鄉、埤頭鄉 [雲林縣] 西螺鎮"
  },
  {
    "斷層名稱": "大甲斷層全段",
    "r": ">=14",
    "SDS": "0.7",
    "SD1": "0.4",
    "SMS": "0.9",
    "SM1": "0.5",
    "對應鄉鎮": "[苗栗縣] 通霄鎮 [彰化縣] 鹿港鎮、溪湖鎮、福興鄉、埔鹽鄉、埤頭鄉 [雲林縣] 西螺鎮"
  },
  {
    "斷層名稱": "鐵砧山斷層",
    "r": "<=1",
    "SDS": "1.08",
    "SD1": "0.63",
    "SMS": "1.33",
    "SM1": "0.83",
    "對應鄉鎮": "[苗栗縣] 苑裡鎮、三義鄉 [臺中市] 中區、西區、南區、北區、西屯區、北屯區、南屯區、豐原區、大甲區、后里區、清水區、沙鹿區、梧棲區、神岡區、潭子區、大雅區、外埔區、大安區、烏日區、大肚區、龍井區、霧峰區、大里區 [彰化縣] 彰化市、和美鎮、北斗鎮、員林市、田中鎮、線西鄉、伸港鄉、秀水鄉、花壇鄉、芬園鄉、大村鄉、埔心鄉、永靖鄉、社頭鄉、二水鄉、田尾鄉、溪州鄉 [南投縣] 南投市、草屯鎮、竹山鎮、名間鄉、中寮鄉 [雲林縣] 斗六市、莿桐鄉、林內鄉"
  },
  {
    "斷層名稱": "鐵砧山斷層",
    "r": "3",
    "SDS": "1.02",
    "SD1": "0.58",
    "SMS": "1.21",
    "SM1": "0.75",
    "對應鄉鎮": "[苗栗縣] 苑裡鎮、三義鄉 [臺中市] 中區、西區、南區、北區、西屯區、北屯區、南屯區、豐原區、大甲區、后里區、清水區、沙鹿區、梧棲區、神岡區、潭子區、大雅區、外埔區、大安區、烏日區、大肚區、龍井區、霧峰區、大里區 [彰化縣] 彰化市、和美鎮、北斗鎮、員林市、田中鎮、線西鄉、伸港鄉、秀水鄉、花壇鄉、芬園鄉、大村鄉、埔心鄉、永靖鄉、社頭鄉、二水鄉、田尾鄉、溪州鄉 [南投縣] 南投市、草屯鎮、竹山鎮、名間鄉、中寮鄉 [雲林縣] 斗六市、莿桐鄉、林內鄉"
  },
  {
    "斷層名稱": "鐵砧山斷層",
    "r": "5",
    "SDS": "0.94",
    "SD1": "0.53",
    "SMS": "1.14",
    "SM1": "0.69",
    "對應鄉鎮": "[苗栗縣] 苑裡鎮、三義鄉 [臺中市] 中區、西區、南區、北區、西屯區、北屯區、南屯區、豐原區、大甲區、后里區、清水區、沙鹿區、梧棲區、神岡區、潭子區、大雅區、外埔區、大安區、烏日區、大肚區、龍井區、霧峰區、大里區 [彰化縣] 彰化市、和美鎮、北斗鎮、員林市、田中鎮、線西鄉、伸港鄉、秀水鄉、花壇鄉、芬園鄉、大村鄉、埔心鄉、永靖鄉、社頭鄉、二水鄉、田尾鄉、溪州鄉 [南投縣] 南投市、草屯鎮、竹山鎮、名間鄉、中寮鄉 [雲林縣] 斗六市、莿桐鄉、林內鄉"
  },
  {
    "斷層名稱": "鐵砧山斷層",
    "r": "7",
    "SDS": "0.87",
    "SD1": "0.49",
    "SMS": "1.09",
    "SM1": "0.65",
    "對應鄉鎮": "[苗栗縣] 苑裡鎮、三義鄉 [臺中市] 中區、西區、南區、北區、西屯區、北屯區、南屯區、豐原區、大甲區、后里區、清水區、沙鹿區、梧棲區、神岡區、潭子區、大雅區、外埔區、大安區、烏日區、大肚區、龍井區、霧峰區、大里區 [彰化縣] 彰化市、和美鎮、北斗鎮、員林市、田中鎮、線西鄉、伸港鄉、秀水鄉、花壇鄉、芬園鄉、大村鄉、埔心鄉、永靖鄉、社頭鄉、二水鄉、田尾鄉、溪州鄉 [南投縣] 南投市、草屯鎮、竹山鎮、名間鄉、中寮鄉 [雲林縣] 斗六市、莿桐鄉、林內鄉"
  },
  {
    "斷層名稱": "鐵砧山斷層",
    "r": "9",
    "SDS": "0.85",
    "SD1": "0.48",
    "SMS": "1.06",
    "SM1": "0.62",
    "對應鄉鎮": "[苗栗縣] 苑裡鎮、三義鄉 [臺中市] 中區、西區、南區、北區、西屯區、北屯區、南屯區、豐原區、大甲區、后里區、清水區、沙鹿區、梧棲區、神岡區、潭子區、大雅區、外埔區、大安區、烏日區、大肚區、龍井區、霧峰區、大里區 [彰化縣] 彰化市、和美鎮、北斗鎮、員林市、田中鎮、線西鄉、伸港鄉、秀水鄉、花壇鄉、芬園鄉、大村鄉、埔心鄉、永靖鄉、社頭鄉、二水鄉、田尾鄉、溪州鄉 [南投縣] 南投市、草屯鎮、竹山鎮、名間鄉、中寮鄉 [雲林縣] 斗六市、莿桐鄉、林內鄉"
  },
  {
    "斷層名稱": "鐵砧山斷層",
    "r": "11",
    "SDS": "0.83",
    "SD1": "0.46",
    "SMS": "1.03",
    "SM1": "0.59",
    "對應鄉鎮": "[苗栗縣] 苑裡鎮、三義鄉 [臺中市] 中區、西區、南區、北區、西屯區、北屯區、南屯區、豐原區、大甲區、后里區、清水區、沙鹿區、梧棲區、神岡區、潭子區、大雅區、外埔區、大安區、烏日區、大肚區、龍井區、霧峰區、大里區 [彰化縣] 彰化市、和美鎮、北斗鎮、員林市、田中鎮、線西鄉、伸港鄉、秀水鄉、花壇鄉、芬園鄉、大村鄉、埔心鄉、永靖鄉、社頭鄉、二水鄉、田尾鄉、溪州鄉 [南投縣] 南投市、草屯鎮、竹山鎮、名間鄉、中寮鄉 [雲林縣] 斗六市、莿桐鄉、林內鄉"
  },
  {
    "斷層名稱": "鐵砧山斷層",
    "r": "13",
    "SDS": "0.8",
    "SD1": "0.45",
    "SMS": "1",
    "SM1": "0.55",
    "對應鄉鎮": "[苗栗縣] 苑裡鎮、三義鄉 [臺中市] 中區、西區、南區、北區、西屯區、北屯區、南屯區、豐原區、大甲區、后里區、清水區、沙鹿區、梧棲區、神岡區、潭子區、大雅區、外埔區、大安區、烏日區、大肚區、龍井區、霧峰區、大里區 [彰化縣] 彰化市、和美鎮、北斗鎮、員林市、田中鎮、線西鄉、伸港鄉、秀水鄉、花壇鄉、芬園鄉、大村鄉、埔心鄉、永靖鄉、社頭鄉、二水鄉、田尾鄉、溪州鄉 [南投縣] 南投市、草屯鎮、竹山鎮、名間鄉、中寮鄉 [雲林縣] 斗六市、莿桐鄉、林內鄉"
  },
  {
    "斷層名稱": "鐵砧山斷層",
    "r": ">=14",
    "SDS": "0.8",
    "SD1": "0.45",
    "SMS": "1",
    "SM1": "0.55",
    "對應鄉鎮": "[苗栗縣] 苑裡鎮、三義鄉 [臺中市] 中區、西區、南區、北區、西屯區、北屯區、南屯區、豐原區、大甲區、后里區、清水區、沙鹿區、梧棲區、神岡區、潭子區、大雅區、外埔區、大安區、烏日區、大肚區、龍井區、霧峰區、大里區 [彰化縣] 彰化市、和美鎮、北斗鎮、員林市、田中鎮、線西鄉、伸港鄉、秀水鄉、花壇鄉、芬園鄉、大村鄉、埔心鄉、永靖鄉、社頭鄉、二水鄉、田尾鄉、溪州鄉 [南投縣] 南投市、草屯鎮、竹山鎮、名間鄉、中寮鄉 [雲林縣] 斗六市、莿桐鄉、林內鄉"
  },
  {
    "斷層名稱": "鐵砧山斷層",
    "r": "<=1",
    "SDS": "1.08",
    "SD1": "0.63",
    "SMS": "1.33",
    "SM1": "0.83",
    "對應鄉鎮": "[苗栗縣] 通霄鎮 [彰化縣] 鹿港鎮、溪湖鎮、福興鄉、埔鹽鄉、埤頭鄉 [雲林縣] 西螺鎮"
  },
  {
    "斷層名稱": "鐵砧山斷層",
    "r": "3",
    "SDS": "1.02",
    "SD1": "0.58",
    "SMS": "1.21",
    "SM1": "0.75",
    "對應鄉鎮": "[苗栗縣] 通霄鎮 [彰化縣] 鹿港鎮、溪湖鎮、福興鄉、埔鹽鄉、埤頭鄉 [雲林縣] 西螺鎮"
  },
  {
    "斷層名稱": "鐵砧山斷層",
    "r": "5",
    "SDS": "0.94",
    "SD1": "0.53",
    "SMS": "1.14",
    "SM1": "0.69",
    "對應鄉鎮": "[苗栗縣] 通霄鎮 [彰化縣] 鹿港鎮、溪湖鎮、福興鄉、埔鹽鄉、埤頭鄉 [雲林縣] 西螺鎮"
  },
  {
    "斷層名稱": "鐵砧山斷層",
    "r": "7",
    "SDS": "0.87",
    "SD1": "0.49",
    "SMS": "1.09",
    "SM1": "0.65",
    "對應鄉鎮": "[苗栗縣] 通霄鎮 [彰化縣] 鹿港鎮、溪湖鎮、福興鄉、埔鹽鄉、埤頭鄉 [雲林縣] 西螺鎮"
  },
  {
    "斷層名稱": "鐵砧山斷層",
    "r": "9",
    "SDS": "0.85",
    "SD1": "0.48",
    "SMS": "1.06",
    "SM1": "0.62",
    "對應鄉鎮": "[苗栗縣] 通霄鎮 [彰化縣] 鹿港鎮、溪湖鎮、福興鄉、埔鹽鄉、埤頭鄉 [雲林縣] 西螺鎮"
  },
  {
    "斷層名稱": "鐵砧山斷層",
    "r": "11",
    "SDS": "0.83",
    "SD1": "0.46",
    "SMS": "1.03",
    "SM1": "0.59",
    "對應鄉鎮": "[苗栗縣] 通霄鎮 [彰化縣] 鹿港鎮、溪湖鎮、福興鄉、埔鹽鄉、埤頭鄉 [雲林縣] 西螺鎮"
  },
  {
    "斷層名稱": "鐵砧山斷層",
    "r": "13",
    "SDS": "0.8",
    "SD1": "0.45",
    "SMS": "1",
    "SM1": "0.55",
    "對應鄉鎮": "[苗栗縣] 通霄鎮 [彰化縣] 鹿港鎮、溪湖鎮、福興鄉、埔鹽鄉、埤頭鄉 [雲林縣] 西螺鎮"
  },
  {
    "斷層名稱": "鐵砧山斷層",
    "r": ">=14",
    "SDS": "0.7",
    "SD1": "0.4",
    "SMS": "0.9",
    "SM1": "0.5",
    "對應鄉鎮": "[苗栗縣] 通霄鎮 [彰化縣] 鹿港鎮、溪湖鎮、福興鄉、埔鹽鄉、埤頭鄉 [雲林縣] 西螺鎮"
  },
  {
    "斷層名稱": "彰化斷層",
    "r": "<=1",
    "SDS": "1.08",
    "SD1": "0.63",
    "SMS": "1.33",
    "SM1": "0.83",
    "對應鄉鎮": "[苗栗縣] 苑裡鎮、三義鄉 [臺中市] 中區、西區、南區、北區、西屯區、北屯區、南屯區、豐原區、大甲區、后里區、清水區、沙鹿區、梧棲區、神岡區、潭子區、大雅區、外埔區、大安區、烏日區、大肚區、龍井區、霧峰區、大里區 [彰化縣] 彰化市、和美鎮、北斗鎮、員林市、田中鎮、線西鄉、伸港鄉、秀水鄉、花壇鄉、芬園鄉、大村鄉、埔心鄉、永靖鄉、社頭鄉、二水鄉、田尾鄉、溪州鄉 [南投縣] 南投市、草屯鎮、竹山鎮、名間鄉、中寮鄉 [雲林縣] 斗六市、莿桐鄉、林內鄉"
  },
  {
    "斷層名稱": "彰化斷層",
    "r": "3",
    "SDS": "1.02",
    "SD1": "0.58",
    "SMS": "1.21",
    "SM1": "0.75",
    "對應鄉鎮": "[苗栗縣] 苑裡鎮、三義鄉 [臺中市] 中區、西區、南區、北區、西屯區、北屯區、南屯區、豐原區、大甲區、后里區、清水區、沙鹿區、梧棲區、神岡區、潭子區、大雅區、外埔區、大安區、烏日區、大肚區、龍井區、霧峰區、大里區 [彰化縣] 彰化市、和美鎮、北斗鎮、員林市、田中鎮、線西鄉、伸港鄉、秀水鄉、花壇鄉、芬園鄉、大村鄉、埔心鄉、永靖鄉、社頭鄉、二水鄉、田尾鄉、溪州鄉 [南投縣] 南投市、草屯鎮、竹山鎮、名間鄉、中寮鄉 [雲林縣] 斗六市、莿桐鄉、林內鄉"
  },
  {
    "斷層名稱": "彰化斷層",
    "r": "5",
    "SDS": "0.94",
    "SD1": "0.53",
    "SMS": "1.14",
    "SM1": "0.69",
    "對應鄉鎮": "[苗栗縣] 苑裡鎮、三義鄉 [臺中市] 中區、西區、南區、北區、西屯區、北屯區、南屯區、豐原區、大甲區、后里區、清水區、沙鹿區、梧棲區、神岡區、潭子區、大雅區、外埔區、大安區、烏日區、大肚區、龍井區、霧峰區、大里區 [彰化縣] 彰化市、和美鎮、北斗鎮、員林市、田中鎮、線西鄉、伸港鄉、秀水鄉、花壇鄉、芬園鄉、大村鄉、埔心鄉、永靖鄉、社頭鄉、二水鄉、田尾鄉、溪州鄉 [南投縣] 南投市、草屯鎮、竹山鎮、名間鄉、中寮鄉 [雲林縣] 斗六市、莿桐鄉、林內鄉"
  },
  {
    "斷層名稱": "彰化斷層",
    "r": "7",
    "SDS": "0.87",
    "SD1": "0.49",
    "SMS": "1.09",
    "SM1": "0.65",
    "對應鄉鎮": "[苗栗縣] 苑裡鎮、三義鄉 [臺中市] 中區、西區、南區、北區、西屯區、北屯區、南屯區、豐原區、大甲區、后里區、清水區、沙鹿區、梧棲區、神岡區、潭子區、大雅區、外埔區、大安區、烏日區、大肚區、龍井區、霧峰區、大里區 [彰化縣] 彰化市、和美鎮、北斗鎮、員林市、田中鎮、線西鄉、伸港鄉、秀水鄉、花壇鄉、芬園鄉、大村鄉、埔心鄉、永靖鄉、社頭鄉、二水鄉、田尾鄉、溪州鄉 [南投縣] 南投市、草屯鎮、竹山鎮、名間鄉、中寮鄉 [雲林縣] 斗六市、莿桐鄉、林內鄉"
  },
  {
    "斷層名稱": "彰化斷層",
    "r": "9",
    "SDS": "0.85",
    "SD1": "0.48",
    "SMS": "1.06",
    "SM1": "0.62",
    "對應鄉鎮": "[苗栗縣] 苑裡鎮、三義鄉 [臺中市] 中區、西區、南區、北區、西屯區、北屯區、南屯區、豐原區、大甲區、后里區、清水區、沙鹿區、梧棲區、神岡區、潭子區、大雅區、外埔區、大安區、烏日區、大肚區、龍井區、霧峰區、大里區 [彰化縣] 彰化市、和美鎮、北斗鎮、員林市、田中鎮、線西鄉、伸港鄉、秀水鄉、花壇鄉、芬園鄉、大村鄉、埔心鄉、永靖鄉、社頭鄉、二水鄉、田尾鄉、溪州鄉 [南投縣] 南投市、草屯鎮、竹山鎮、名間鄉、中寮鄉 [雲林縣] 斗六市、莿桐鄉、林內鄉"
  },
  {
    "斷層名稱": "彰化斷層",
    "r": "11",
    "SDS": "0.83",
    "SD1": "0.46",
    "SMS": "1.03",
    "SM1": "0.59",
    "對應鄉鎮": "[苗栗縣] 苑裡鎮、三義鄉 [臺中市] 中區、西區、南區、北區、西屯區、北屯區、南屯區、豐原區、大甲區、后里區、清水區、沙鹿區、梧棲區、神岡區、潭子區、大雅區、外埔區、大安區、烏日區、大肚區、龍井區、霧峰區、大里區 [彰化縣] 彰化市、和美鎮、北斗鎮、員林市、田中鎮、線西鄉、伸港鄉、秀水鄉、花壇鄉、芬園鄉、大村鄉、埔心鄉、永靖鄉、社頭鄉、二水鄉、田尾鄉、溪州鄉 [南投縣] 南投市、草屯鎮、竹山鎮、名間鄉、中寮鄉 [雲林縣] 斗六市、莿桐鄉、林內鄉"
  },
  {
    "斷層名稱": "彰化斷層",
    "r": "13",
    "SDS": "0.8",
    "SD1": "0.45",
    "SMS": "1",
    "SM1": "0.55",
    "對應鄉鎮": "[苗栗縣] 苑裡鎮、三義鄉 [臺中市] 中區、西區、南區、北區、西屯區、北屯區、南屯區、豐原區、大甲區、后里區、清水區、沙鹿區、梧棲區、神岡區、潭子區、大雅區、外埔區、大安區、烏日區、大肚區、龍井區、霧峰區、大里區 [彰化縣] 彰化市、和美鎮、北斗鎮、員林市、田中鎮、線西鄉、伸港鄉、秀水鄉、花壇鄉、芬園鄉、大村鄉、埔心鄉、永靖鄉、社頭鄉、二水鄉、田尾鄉、溪州鄉 [南投縣] 南投市、草屯鎮、竹山鎮、名間鄉、中寮鄉 [雲林縣] 斗六市、莿桐鄉、林內鄉"
  },
  {
    "斷層名稱": "彰化斷層",
    "r": ">=14",
    "SDS": "0.8",
    "SD1": "0.45",
    "SMS": "1",
    "SM1": "0.55",
    "對應鄉鎮": "[苗栗縣] 苑裡鎮、三義鄉 [臺中市] 中區、西區、南區、北區、西屯區、北屯區、南屯區、豐原區、大甲區、后里區、清水區、沙鹿區、梧棲區、神岡區、潭子區、大雅區、外埔區、大安區、烏日區、大肚區、龍井區、霧峰區、大里區 [彰化縣] 彰化市、和美鎮、北斗鎮、員林市、田中鎮、線西鄉、伸港鄉、秀水鄉、花壇鄉、芬園鄉、大村鄉、埔心鄉、永靖鄉、社頭鄉、二水鄉、田尾鄉、溪州鄉 [南投縣] 南投市、草屯鎮、竹山鎮、名間鄉、中寮鄉 [雲林縣] 斗六市、莿桐鄉、林內鄉"
  },
  {
    "斷層名稱": "彰化斷層",
    "r": "<=1",
    "SDS": "1.08",
    "SD1": "0.63",
    "SMS": "1.33",
    "SM1": "0.83",
    "對應鄉鎮": "[苗栗縣] 通霄鎮 [彰化縣] 鹿港鎮、溪湖鎮、福興鄉、埔鹽鄉、埤頭鄉 [雲林縣] 西螺鎮"
  },
  {
    "斷層名稱": "彰化斷層",
    "r": "3",
    "SDS": "1.02",
    "SD1": "0.58",
    "SMS": "1.21",
    "SM1": "0.75",
    "對應鄉鎮": "[苗栗縣] 通霄鎮 [彰化縣] 鹿港鎮、溪湖鎮、福興鄉、埔鹽鄉、埤頭鄉 [雲林縣] 西螺鎮"
  },
  {
    "斷層名稱": "彰化斷層",
    "r": "5",
    "SDS": "0.94",
    "SD1": "0.53",
    "SMS": "1.14",
    "SM1": "0.69",
    "對應鄉鎮": "[苗栗縣] 通霄鎮 [彰化縣] 鹿港鎮、溪湖鎮、福興鄉、埔鹽鄉、埤頭鄉 [雲林縣] 西螺鎮"
  },
  {
    "斷層名稱": "彰化斷層",
    "r": "7",
    "SDS": "0.87",
    "SD1": "0.49",
    "SMS": "1.09",
    "SM1": "0.65",
    "對應鄉鎮": "[苗栗縣] 通霄鎮 [彰化縣] 鹿港鎮、溪湖鎮、福興鄉、埔鹽鄉、埤頭鄉 [雲林縣] 西螺鎮"
  },
  {
    "斷層名稱": "彰化斷層",
    "r": "9",
    "SDS": "0.85",
    "SD1": "0.48",
    "SMS": "1.06",
    "SM1": "0.62",
    "對應鄉鎮": "[苗栗縣] 通霄鎮 [彰化縣] 鹿港鎮、溪湖鎮、福興鄉、埔鹽鄉、埤頭鄉 [雲林縣] 西螺鎮"
  },
  {
    "斷層名稱": "彰化斷層",
    "r": "11",
    "SDS": "0.83",
    "SD1": "0.46",
    "SMS": "1.03",
    "SM1": "0.59",
    "對應鄉鎮": "[苗栗縣] 通霄鎮 [彰化縣] 鹿港鎮、溪湖鎮、福興鄉、埔鹽鄉、埤頭鄉 [雲林縣] 西螺鎮"
  },
  {
    "斷層名稱": "彰化斷層",
    "r": "13",
    "SDS": "0.8",
    "SD1": "0.45",
    "SMS": "1",
    "SM1": "0.55",
    "對應鄉鎮": "[苗栗縣] 通霄鎮 [彰化縣] 鹿港鎮、溪湖鎮、福興鄉、埔鹽鄉、埤頭鄉 [雲林縣] 西螺鎮"
  },
  {
    "斷層名稱": "彰化斷層",
    "r": ">=14",
    "SDS": "0.7",
    "SD1": "0.4",
    "SMS": "0.9",
    "SM1": "0.5",
    "對應鄉鎮": "[苗栗縣] 通霄鎮 [彰化縣] 鹿港鎮、溪湖鎮、福興鄉、埔鹽鄉、埤頭鄉 [雲林縣] 西螺鎮"
  },
  {
    "斷層名稱": "屯子腳斷層",
    "r": "<=1",
    "SDS": "1.02",
    "SD1": "0.59",
    "SMS": "1.26",
    "SM1": "0.78",
    "對應鄉鎮": "[苗栗縣] 苑裡鎮、銅鑼鄉、三義鄉、大湖鄉、卓蘭鎮 [臺中市] 西屯區、北屯區、豐原區、東勢區、大甲區、后里區、清水區、沙鹿區、梧棲區、神岡區、潭子區、大雅區、新社區、石岡區、外埔區、大安區、龍井區"
  },
  {
    "斷層名稱": "屯子腳斷層",
    "r": "3",
    "SDS": "0.97",
    "SD1": "0.57",
    "SMS": "1.19",
    "SM1": "0.74",
    "對應鄉鎮": "[苗栗縣] 苑裡鎮、銅鑼鄉、三義鄉、大湖鄉、卓蘭鎮 [臺中市] 西屯區、北屯區、豐原區、東勢區、大甲區、后里區、清水區、沙鹿區、梧棲區、神岡區、潭子區、大雅區、新社區、石岡區、外埔區、大安區、龍井區"
  },
  {
    "斷層名稱": "屯子腳斷層",
    "r": "5",
    "SDS": "0.93",
    "SD1": "0.55",
    "SMS": "1.13",
    "SM1": "0.69",
    "對應鄉鎮": "[苗栗縣] 苑裡鎮、銅鑼鄉、三義鄉、大湖鄉、卓蘭鎮 [臺中市] 西屯區、北屯區、豐原區、東勢區、大甲區、后里區、清水區、沙鹿區、梧棲區、神岡區、潭子區、大雅區、新社區、石岡區、外埔區、大安區、龍井區"
  },
  {
    "斷層名稱": "屯子腳斷層",
    "r": "7",
    "SDS": "0.89",
    "SD1": "0.52",
    "SMS": "1.07",
    "SM1": "0.64",
    "對應鄉鎮": "[苗栗縣] 苑裡鎮、銅鑼鄉、三義鄉、大湖鄉、卓蘭鎮 [臺中市] 西屯區、北屯區、豐原區、東勢區、大甲區、后里區、清水區、沙鹿區、梧棲區、神岡區、潭子區、大雅區、新社區、石岡區、外埔區、大安區、龍井區"
  },
  {
    "斷層名稱": "屯子腳斷層",
    "r": "9",
    "SDS": "0.85",
    "SD1": "0.49",
    "SMS": "1.03",
    "SM1": "0.6",
    "對應鄉鎮": "[苗栗縣] 苑裡鎮、銅鑼鄉、三義鄉、大湖鄉、卓蘭鎮 [臺中市] 西屯區、北屯區、豐原區、東勢區、大甲區、后里區、清水區、沙鹿區、梧棲區、神岡區、潭子區、大雅區、新社區、石岡區、外埔區、大安區、龍井區"
  },
  {
    "斷層名稱": "屯子腳斷層",
    "r": "11",
    "SDS": "0.8",
    "SD1": "0.45",
    "SMS": "1",
    "SM1": "0.55",
    "對應鄉鎮": "[苗栗縣] 苑裡鎮、銅鑼鄉、三義鄉、大湖鄉、卓蘭鎮 [臺中市] 西屯區、北屯區、豐原區、東勢區、大甲區、后里區、清水區、沙鹿區、梧棲區、神岡區、潭子區、大雅區、新社區、石岡區、外埔區、大安區、龍井區"
  },
  {
    "斷層名稱": "屯子腳斷層",
    "r": "13",
    "SDS": "0.8",
    "SD1": "0.45",
    "SMS": "1",
    "SM1": "0.55",
    "對應鄉鎮": "[苗栗縣] 苑裡鎮、銅鑼鄉、三義鄉、大湖鄉、卓蘭鎮 [臺中市] 西屯區、北屯區、豐原區、東勢區、大甲區、后里區、清水區、沙鹿區、梧棲區、神岡區、潭子區、大雅區、新社區、石岡區、外埔區、大安區、龍井區"
  },
  {
    "斷層名稱": "屯子腳斷層",
    "r": ">=14",
    "SDS": "0.8",
    "SD1": "0.45",
    "SMS": "1",
    "SM1": "0.55",
    "對應鄉鎮": "[苗栗縣] 苑裡鎮、銅鑼鄉、三義鄉、大湖鄉、卓蘭鎮 [臺中市] 西屯區、北屯區、豐原區、東勢區、大甲區、后里區、清水區、沙鹿區、梧棲區、神岡區、潭子區、大雅區、新社區、石岡區、外埔區、大安區、龍井區"
  },
  {
    "斷層名稱": "屯子腳斷層",
    "r": "<=1",
    "SDS": "1.02",
    "SD1": "0.59",
    "SMS": "1.26",
    "SM1": "0.78",
    "對應鄉鎮": "[苗栗縣] 通霄鎮"
  },
  {
    "斷層名稱": "屯子腳斷層",
    "r": "3",
    "SDS": "0.97",
    "SD1": "0.57",
    "SMS": "1.19",
    "SM1": "0.74",
    "對應鄉鎮": "[苗栗縣] 通霄鎮"
  },
  {
    "斷層名稱": "屯子腳斷層",
    "r": "5",
    "SDS": "0.93",
    "SD1": "0.55",
    "SMS": "1.13",
    "SM1": "0.69",
    "對應鄉鎮": "[苗栗縣] 通霄鎮"
  },
  {
    "斷層名稱": "屯子腳斷層",
    "r": "7",
    "SDS": "0.89",
    "SD1": "0.52",
    "SMS": "1.07",
    "SM1": "0.64",
    "對應鄉鎮": "[苗栗縣] 通霄鎮"
  },
  {
    "斷層名稱": "屯子腳斷層",
    "r": "9",
    "SDS": "0.85",
    "SD1": "0.49",
    "SMS": "1.03",
    "SM1": "0.6",
    "對應鄉鎮": "[苗栗縣] 通霄鎮"
  },
  {
    "斷層名稱": "屯子腳斷層",
    "r": "11",
    "SDS": "0.7",
    "SD1": "0.4",
    "SMS": "0.9",
    "SM1": "0.5",
    "對應鄉鎮": "[苗栗縣] 通霄鎮"
  },
  {
    "斷層名稱": "屯子腳斷層",
    "r": "13",
    "SDS": "0.7",
    "SD1": "0.4",
    "SMS": "0.9",
    "SM1": "0.5",
    "對應鄉鎮": "[苗栗縣] 通霄鎮"
  },
  {
    "斷層名稱": "屯子腳斷層",
    "r": ">=14",
    "SDS": "0.7",
    "SD1": "0.4",
    "SMS": "0.9",
    "SM1": "0.5",
    "對應鄉鎮": "[苗栗縣] 通霄鎮"
  },
  {
    "斷層名稱": "車籠埔斷層全段",
    "r": "<=1",
    "SDS": "0.98",
    "SD1": "0.61",
    "SMS": "1.25",
    "SM1": "0.83",
    "對應鄉鎮": "[苗栗縣] 苑裡鎮、銅鑼鄉、三義鄉、大湖鄉、卓蘭鎮 [臺中市] 中區、東區、西區、南區、北區、西屯區、北屯區、南屯區、豐原區、東勢區、后里區、清水區、沙鹿區、神岡區、潭子區、大雅區、新社區、石岡區、外埔區、太平區、烏日區、霧峰區、大里區 [彰化縣] 彰化市、員林市、田中鎮、花壇鄉、芬園鄉、大村鄉、社頭鄉、二水鄉 [南投縣] 南投市、草屯鎮、竹山鎮、名間鄉、中寮鄉、集集鎮、鹿谷鄉、國姓鄉、水里鄉 [雲林縣] 斗六市、林內鄉、古坑鄉 [嘉義縣] 大林鎮、竹崎鄉、梅山鄉"
  },
  {
    "斷層名稱": "車籠埔斷層全段",
    "r": "3",
    "SDS": "0.94",
    "SD1": "0.6",
    "SMS": "1.21",
    "SM1": "0.8",
    "對應鄉鎮": "[苗栗縣] 苑裡鎮、銅鑼鄉、三義鄉、大湖鄉、卓蘭鎮 [臺中市] 中區、東區、西區、南區、北區、西屯區、北屯區、南屯區、豐原區、東勢區、后里區、清水區、沙鹿區、神岡區、潭子區、大雅區、新社區、石岡區、外埔區、太平區、烏日區、霧峰區、大里區 [彰化縣] 彰化市、員林市、田中鎮、花壇鄉、芬園鄉、大村鄉、社頭鄉、二水鄉 [南投縣] 南投市、草屯鎮、竹山鎮、名間鄉、中寮鄉、集集鎮、鹿谷鄉、國姓鄉、水里鄉 [雲林縣] 斗六市、林內鄉、古坑鄉 [嘉義縣] 大林鎮、竹崎鄉、梅山鄉"
  },
  {
    "斷層名稱": "車籠埔斷層全段",
    "r": "5",
    "SDS": "0.89",
    "SD1": "0.57",
    "SMS": "1.15",
    "SM1": "0.76",
    "對應鄉鎮": "[苗栗縣] 苑裡鎮、銅鑼鄉、三義鄉、大湖鄉、卓蘭鎮 [臺中市] 中區、東區、西區、南區、北區、西屯區、北屯區、南屯區、豐原區、東勢區、后里區、清水區、沙鹿區、神岡區、潭子區、大雅區、新社區、石岡區、外埔區、太平區、烏日區、霧峰區、大里區 [彰化縣] 彰化市、員林市、田中鎮、花壇鄉、芬園鄉、大村鄉、社頭鄉、二水鄉 [南投縣] 南投市、草屯鎮、竹山鎮、名間鄉、中寮鄉、集集鎮、鹿谷鄉、國姓鄉、水里鄉 [雲林縣] 斗六市、林內鄉、古坑鄉 [嘉義縣] 大林鎮、竹崎鄉、梅山鄉"
  },
  {
    "斷層名稱": "車籠埔斷層全段",
    "r": "7",
    "SDS": "0.85",
    "SD1": "0.54",
    "SMS": "1.09",
    "SM1": "0.7",
    "對應鄉鎮": "[苗栗縣] 苑裡鎮、銅鑼鄉、三義鄉、大湖鄉、卓蘭鎮 [臺中市] 中區、東區、西區、南區、北區、西屯區、北屯區、南屯區、豐原區、東勢區、后里區、清水區、沙鹿區、神岡區、潭子區、大雅區、新社區、石岡區、外埔區、太平區、烏日區、霧峰區、大里區 [彰化縣] 彰化市、員林市、田中鎮、花壇鄉、芬園鄉、大村鄉、社頭鄉、二水鄉 [南投縣] 南投市、草屯鎮、竹山鎮、名間鄉、中寮鄉、集集鎮、鹿谷鄉、國姓鄉、水里鄉 [雲林縣] 斗六市、林內鄉、古坑鄉 [嘉義縣] 大林鎮、竹崎鄉、梅山鄉"
  },
  {
    "斷層名稱": "車籠埔斷層全段",
    "r": "9",
    "SDS": "0.83",
    "SD1": "0.51",
    "SMS": "1.05",
    "SM1": "0.66",
    "對應鄉鎮": "[苗栗縣] 苑裡鎮、銅鑼鄉、三義鄉、大湖鄉、卓蘭鎮 [臺中市] 中區、東區、西區、南區、北區、西屯區、北屯區、南屯區、豐原區、東勢區、后里區、清水區、沙鹿區、神岡區、潭子區、大雅區、新社區、石岡區、外埔區、太平區、烏日區、霧峰區、大里區 [彰化縣] 彰化市、員林市、田中鎮、花壇鄉、芬園鄉、大村鄉、社頭鄉、二水鄉 [南投縣] 南投市、草屯鎮、竹山鎮、名間鄉、中寮鄉、集集鎮、鹿谷鄉、國姓鄉、水里鄉 [雲林縣] 斗六市、林內鄉、古坑鄉 [嘉義縣] 大林鎮、竹崎鄉、梅山鄉"
  },
  {
    "斷層名稱": "車籠埔斷層全段",
    "r": "11",
    "SDS": "0.82",
    "SD1": "0.48",
    "SMS": "1.02",
    "SM1": "0.61",
    "對應鄉鎮": "[苗栗縣] 苑裡鎮、銅鑼鄉、三義鄉、大湖鄉、卓蘭鎮 [臺中市] 中區、東區、西區、南區、北區、西屯區、北屯區、南屯區、豐原區、東勢區、后里區、清水區、沙鹿區、神岡區、潭子區、大雅區、新社區、石岡區、外埔區、太平區、烏日區、霧峰區、大里區 [彰化縣] 彰化市、員林市、田中鎮、花壇鄉、芬園鄉、大村鄉、社頭鄉、二水鄉 [南投縣] 南投市、草屯鎮、竹山鎮、名間鄉、中寮鄉、集集鎮、鹿谷鄉、國姓鄉、水里鄉 [雲林縣] 斗六市、林內鄉、古坑鄉 [嘉義縣] 大林鎮、竹崎鄉、梅山鄉"
  },
  {
    "斷層名稱": "車籠埔斷層全段",
    "r": "13",
    "SDS": "0.8",
    "SD1": "0.45",
    "SMS": "1",
    "SM1": "0.55",
    "對應鄉鎮": "[苗栗縣] 苑裡鎮、銅鑼鄉、三義鄉、大湖鄉、卓蘭鎮 [臺中市] 中區、東區、西區、南區、北區、西屯區、北屯區、南屯區、豐原區、東勢區、后里區、清水區、沙鹿區、神岡區、潭子區、大雅區、新社區、石岡區、外埔區、太平區、烏日區、霧峰區、大里區 [彰化縣] 彰化市、員林市、田中鎮、花壇鄉、芬園鄉、大村鄉、社頭鄉、二水鄉 [南投縣] 南投市、草屯鎮、竹山鎮、名間鄉、中寮鄉、集集鎮、鹿谷鄉、國姓鄉、水里鄉 [雲林縣] 斗六市、林內鄉、古坑鄉 [嘉義縣] 大林鎮、竹崎鄉、梅山鄉"
  },
  {
    "斷層名稱": "車籠埔斷層全段",
    "r": ">=14",
    "SDS": "0.8",
    "SD1": "0.45",
    "SMS": "1",
    "SM1": "0.55",
    "對應鄉鎮": "[苗栗縣] 苑裡鎮、銅鑼鄉、三義鄉、大湖鄉、卓蘭鎮 [臺中市] 中區、東區、西區、南區、北區、西屯區、北屯區、南屯區、豐原區、東勢區、后里區、清水區、沙鹿區、神岡區、潭子區、大雅區、新社區、石岡區、外埔區、太平區、烏日區、霧峰區、大里區 [彰化縣] 彰化市、員林市、田中鎮、花壇鄉、芬園鄉、大村鄉、社頭鄉、二水鄉 [南投縣] 南投市、草屯鎮、竹山鎮、名間鄉、中寮鄉、集集鎮、鹿谷鄉、國姓鄉、水里鄉 [雲林縣] 斗六市、林內鄉、古坑鄉 [嘉義縣] 大林鎮、竹崎鄉、梅山鄉"
  },
  {
    "斷層名稱": "車籠埔斷層全段",
    "r": "<=1",
    "SDS": "0.98",
    "SD1": "0.61",
    "SMS": "1.25",
    "SM1": "0.83",
    "對應鄉鎮": "[苗栗縣] 泰安鄉 [臺中市] 和平區"
  },
  {
    "斷層名稱": "車籠埔斷層全段",
    "r": "3",
    "SDS": "0.94",
    "SD1": "0.6",
    "SMS": "1.21",
    "SM1": "0.8",
    "對應鄉鎮": "[苗栗縣] 泰安鄉 [臺中市] 和平區"
  },
  {
    "斷層名稱": "車籠埔斷層全段",
    "r": "5",
    "SDS": "0.89",
    "SD1": "0.57",
    "SMS": "1.15",
    "SM1": "0.76",
    "對應鄉鎮": "[苗栗縣] 泰安鄉 [臺中市] 和平區"
  },
  {
    "斷層名稱": "車籠埔斷層全段",
    "r": "7",
    "SDS": "0.85",
    "SD1": "0.54",
    "SMS": "1.09",
    "SM1": "0.7",
    "對應鄉鎮": "[苗栗縣] 泰安鄉 [臺中市] 和平區"
  },
  {
    "斷層名稱": "車籠埔斷層全段",
    "r": "9",
    "SDS": "0.83",
    "SD1": "0.51",
    "SMS": "1.05",
    "SM1": "0.66",
    "對應鄉鎮": "[苗栗縣] 泰安鄉 [臺中市] 和平區"
  },
  {
    "斷層名稱": "車籠埔斷層全段",
    "r": "11",
    "SDS": "0.82",
    "SD1": "0.48",
    "SMS": "1.02",
    "SM1": "0.61",
    "對應鄉鎮": "[苗栗縣] 泰安鄉 [臺中市] 和平區"
  },
  {
    "斷層名稱": "車籠埔斷層全段",
    "r": "13",
    "SDS": "0.8",
    "SD1": "0.45",
    "SMS": "1",
    "SM1": "0.55",
    "對應鄉鎮": "[苗栗縣] 泰安鄉 [臺中市] 和平區"
  },
  {
    "斷層名稱": "車籠埔斷層全段",
    "r": ">=14",
    "SDS": "0.7",
    "SD1": "0.4",
    "SMS": "0.9",
    "SM1": "0.5",
    "對應鄉鎮": "[苗栗縣] 泰安鄉 [臺中市] 和平區"
  },
  {
    "斷層名稱": "大茅埔-雙冬斷層",
    "r": "<=1",
    "SDS": "1.08",
    "SD1": "0.63",
    "SMS": "1.25",
    "SM1": "0.83",
    "對應鄉鎮": "[苗栗縣] 大湖鄉、卓蘭鎮 [臺中市] 東區、中區、西區、南區、北區、北屯區、豐原區、東勢區、潭子區、新社區、石岡區、霧峰區、太平區、大里區 [南投縣] 南投市、草屯鎮、竹山鎮、名間鄉、中寮鄉、集集鎮、鹿谷鄉、國姓鄉、水里鄉"
  },
  {
    "斷層名稱": "大茅埔-雙冬斷層",
    "r": "3",
    "SDS": "1.02",
    "SD1": "0.58",
    "SMS": "1.17",
    "SM1": "0.76",
    "對應鄉鎮": "[苗栗縣] 大湖鄉、卓蘭鎮 [臺中市] 東區、中區、西區、南區、北區、北屯區、豐原區、東勢區、潭子區、新社區、石岡區、霧峰區、太平區、大里區 [南投縣] 南投市、草屯鎮、竹山鎮、名間鄉、中寮鄉、集集鎮、鹿谷鄉、國姓鄉、水里鄉"
  },
  {
    "斷層名稱": "大茅埔-雙冬斷層",
    "r": "5",
    "SDS": "0.94",
    "SD1": "0.53",
    "SMS": "1.13",
    "SM1": "0.7",
    "對應鄉鎮": "[苗栗縣] 大湖鄉、卓蘭鎮 [臺中市] 東區、中區、西區、南區、北區、北屯區、豐原區、東勢區、潭子區、新社區、石岡區、霧峰區、太平區、大里區 [南投縣] 南投市、草屯鎮、竹山鎮、名間鄉、中寮鄉、集集鎮、鹿谷鄉、國姓鄉、水里鄉"
  },
  {
    "斷層名稱": "大茅埔-雙冬斷層",
    "r": "7",
    "SDS": "0.87",
    "SD1": "0.49",
    "SMS": "1.09",
    "SM1": "0.65",
    "對應鄉鎮": "[苗栗縣] 大湖鄉、卓蘭鎮 [臺中市] 東區、中區、西區、南區、北區、北屯區、豐原區、東勢區、潭子區、新社區、石岡區、霧峰區、太平區、大里區 [南投縣] 南投市、草屯鎮、竹山鎮、名間鄉、中寮鄉、集集鎮、鹿谷鄉、國姓鄉、水里鄉"
  },
  {
    "斷層名稱": "大茅埔-雙冬斷層",
    "r": "9",
    "SDS": "0.85",
    "SD1": "0.48",
    "SMS": "1.06",
    "SM1": "0.62",
    "對應鄉鎮": "[苗栗縣] 大湖鄉、卓蘭鎮 [臺中市] 東區、中區、西區、南區、北區、北屯區、豐原區、東勢區、潭子區、新社區、石岡區、霧峰區、太平區、大里區 [南投縣] 南投市、草屯鎮、竹山鎮、名間鄉、中寮鄉、集集鎮、鹿谷鄉、國姓鄉、水里鄉"
  },
  {
    "斷層名稱": "大茅埔-雙冬斷層",
    "r": "11",
    "SDS": "0.83",
    "SD1": "0.46",
    "SMS": "1.03",
    "SM1": "0.59",
    "對應鄉鎮": "[苗栗縣] 大湖鄉、卓蘭鎮 [臺中市] 東區、中區、西區、南區、北區、北屯區、豐原區、東勢區、潭子區、新社區、石岡區、霧峰區、太平區、大里區 [南投縣] 南投市、草屯鎮、竹山鎮、名間鄉、中寮鄉、集集鎮、鹿谷鄉、國姓鄉、水里鄉"
  },
  {
    "斷層名稱": "大茅埔-雙冬斷層",
    "r": "13",
    "SDS": "0.8",
    "SD1": "0.45",
    "SMS": "1",
    "SM1": "0.55",
    "對應鄉鎮": "[苗栗縣] 大湖鄉、卓蘭鎮 [臺中市] 東區、中區、西區、南區、北區、北屯區、豐原區、東勢區、潭子區、新社區、石岡區、霧峰區、太平區、大里區 [南投縣] 南投市、草屯鎮、竹山鎮、名間鄉、中寮鄉、集集鎮、鹿谷鄉、國姓鄉、水里鄉"
  },
  {
    "斷層名稱": "大茅埔-雙冬斷層",
    "r": ">=14",
    "SDS": "0.8",
    "SD1": "0.45",
    "SMS": "1",
    "SM1": "0.55",
    "對應鄉鎮": "[苗栗縣] 大湖鄉、卓蘭鎮 [臺中市] 東區、中區、西區、南區、北區、北屯區、豐原區、東勢區、潭子區、新社區、石岡區、霧峰區、太平區、大里區 [南投縣] 南投市、草屯鎮、竹山鎮、名間鄉、中寮鄉、集集鎮、鹿谷鄉、國姓鄉、水里鄉"
  },
  {
    "斷層名稱": "大茅埔-雙冬斷層",
    "r": "<=1",
    "SDS": "1.08",
    "SD1": "0.63",
    "SMS": "1.25",
    "SM1": "0.83",
    "對應鄉鎮": "[苗栗縣] 泰安鄉 [臺中市] 和平區 [南投縣] 埔里鎮、魚池鄉、信義鄉"
  },
  {
    "斷層名稱": "大茅埔-雙冬斷層",
    "r": "3",
    "SDS": "1.02",
    "SD1": "0.58",
    "SMS": "1.17",
    "SM1": "0.76",
    "對應鄉鎮": "[苗栗縣] 泰安鄉 [臺中市] 和平區 [南投縣] 埔里鎮、魚池鄉、信義鄉"
  },
  {
    "斷層名稱": "大茅埔-雙冬斷層",
    "r": "5",
    "SDS": "0.94",
    "SD1": "0.53",
    "SMS": "1.13",
    "SM1": "0.7",
    "對應鄉鎮": "[苗栗縣] 泰安鄉 [臺中市] 和平區 [南投縣] 埔里鎮、魚池鄉、信義鄉"
  },
  {
    "斷層名稱": "大茅埔-雙冬斷層",
    "r": "7",
    "SDS": "0.87",
    "SD1": "0.49",
    "SMS": "1.09",
    "SM1": "0.65",
    "對應鄉鎮": "[苗栗縣] 泰安鄉 [臺中市] 和平區 [南投縣] 埔里鎮、魚池鄉、信義鄉"
  },
  {
    "斷層名稱": "大茅埔-雙冬斷層",
    "r": "9",
    "SDS": "0.85",
    "SD1": "0.48",
    "SMS": "1.06",
    "SM1": "0.62",
    "對應鄉鎮": "[苗栗縣] 泰安鄉 [臺中市] 和平區 [南投縣] 埔里鎮、魚池鄉、信義鄉"
  },
  {
    "斷層名稱": "大茅埔-雙冬斷層",
    "r": "11",
    "SDS": "0.83",
    "SD1": "0.46",
    "SMS": "1.03",
    "SM1": "0.59",
    "對應鄉鎮": "[苗栗縣] 泰安鄉 [臺中市] 和平區 [南投縣] 埔里鎮、魚池鄉、信義鄉"
  },
  {
    "斷層名稱": "大茅埔-雙冬斷層",
    "r": "13",
    "SDS": "0.8",
    "SD1": "0.45",
    "SMS": "1",
    "SM1": "0.55",
    "對應鄉鎮": "[苗栗縣] 泰安鄉 [臺中市] 和平區 [南投縣] 埔里鎮、魚池鄉、信義鄉"
  },
  {
    "斷層名稱": "大茅埔-雙冬斷層",
    "r": ">=14",
    "SDS": "0.7",
    "SD1": "0.4",
    "SMS": "0.9",
    "SM1": "0.5",
    "對應鄉鎮": "[苗栗縣] 泰安鄉 [臺中市] 和平區 [南投縣] 埔里鎮、魚池鄉、信義鄉"
  },
  {
    "斷層名稱": "梅山斷層",
    "r": "<=1",
    "SDS": "1.1",
    "SD1": "0.65",
    "SMS": "1.3",
    "SM1": "0.81",
    "對應鄉鎮": "[雲林縣] 斗六市、古坑鄉 [嘉義縣] 大林鎮、民雄鄉、溪口鄉、竹崎鄉、梅山鄉 [嘉義市] 東區、西區"
  },
  {
    "斷層名稱": "梅山斷層",
    "r": "3",
    "SDS": "1.04",
    "SD1": "0.62",
    "SMS": "1.22",
    "SM1": "0.76",
    "對應鄉鎮": "[雲林縣] 斗六市、古坑鄉 [嘉義縣] 大林鎮、民雄鄉、溪口鄉、竹崎鄉、梅山鄉 [嘉義市] >東區、西區"
  },
  {
    "斷層名稱": "梅山斷層",
    "r": "5",
    "SDS": "0.97",
    "SD1": "0.58",
    "SMS": "1.13",
    "SM1": "0.69",
    "對應鄉鎮": "[雲林縣] 斗六市、古坑鄉 [嘉義縣] 大林鎮、民雄鄉、溪口鄉、竹崎鄉、梅山鄉 [嘉義市] >東區、西區"
  },
  {
    "斷層名稱": "梅山斷層",
    "r": "7",
    "SDS": "0.9",
    "SD1": "0.52",
    "SMS": "1.04",
    "SM1": "0.62",
    "對應鄉鎮": "[雲林縣] 斗六市、古坑鄉 [嘉義縣] 大林鎮、民雄鄉、溪口鄉、竹崎鄉、梅山鄉 [嘉義市] >東區、西區"
  },
  {
    "斷層名稱": "梅山斷層",
    "r": "9",
    "SDS": "0.8",
    "SD1": "0.45",
    "SMS": "1",
    "SM1": "0.55",
    "對應鄉鎮": "[雲林縣] 斗六市、古坑鄉 [嘉義縣] 大林鎮、民雄鄉、溪口鄉、竹崎鄉、梅山鄉 [嘉義市] >東區、西區"
  },
  {
    "斷層名稱": "梅山斷層",
    "r": "11",
    "SDS": "0.8",
    "SD1": "0.45",
    "SMS": "1",
    "SM1": "0.55",
    "對應鄉鎮": "[雲林縣] 斗六市、古坑鄉 [嘉義縣] 大林鎮、民雄鄉、溪口鄉、竹崎鄉、梅山鄉 [嘉義市] >東區、西區"
  },
  {
    "斷層名稱": "梅山斷層",
    "r": "13",
    "SDS": "0.8",
    "SD1": "0.45",
    "SMS": "1",
    "SM1": "0.55",
    "對應鄉鎮": "[雲林縣] 斗六市、古坑鄉 [嘉義縣] 大林鎮、民雄鄉、溪口鄉、竹崎鄉、梅山鄉 [嘉義市] >東區、西區"
  },
  {
    "斷層名稱": "梅山斷層",
    "r": ">=14",
    "SDS": "0.8",
    "SD1": "0.45",
    "SMS": "1",
    "SM1": "0.55",
    "對應鄉鎮": "[雲林縣] 斗六市、古坑鄉 [嘉義縣] 大林鎮、民雄鄉、溪口鄉、竹崎鄉、梅山鄉 [嘉義市] >東區、西區"
  },
  {
    "斷層名稱": "梅山斷層",
    "r": "<=1",
    "SDS": "1.1",
    "SD1": "0.65",
    "SMS": "1.3",
    "SM1": "0.81",
    "對應鄉鎮": "[雲林縣] 斗南鎮、大埤鄉 [嘉義縣] 新港鄉、太保市"
  },
  {
    "斷層名稱": "梅山斷層",
    "r": "3",
    "SDS": "1.04",
    "SD1": "0.62",
    "SMS": "1.22",
    "SM1": "0.76",
    "對應鄉鎮": "[雲林縣] 斗南鎮、大埤鄉 [嘉義縣] 新港鄉、太保市"
  },
  {
    "斷層名稱": "梅山斷層",
    "r": "5",
    "SDS": "0.97",
    "SD1": "0.58",
    "SMS": "1.13",
    "SM1": "0.69",
    "對應鄉鎮": "[雲林縣] 斗南鎮、大埤鄉 [嘉義縣] 新港鄉、太保市"
  },
  {
    "斷層名稱": "梅山斷層",
    "r": "7",
    "SDS": "0.9",
    "SD1": "0.52",
    "SMS": "1.04",
    "SM1": "0.62",
    "對應鄉鎮": "[雲林縣] 斗南鎮、大埤鄉 [嘉義縣] 新港鄉、太保市"
  },
  {
    "斷層名稱": "梅山斷層",
    "r": "9",
    "SDS": "0.7",
    "SD1": "0.4",
    "SMS": "0.9",
    "SM1": "0.5",
    "對應鄉鎮": "[雲林縣] 斗南鎮、大埤鄉 [嘉義縣] 新港鄉、太保市"
  },
  {
    "斷層名稱": "梅山斷層",
    "r": "11",
    "SDS": "0.7",
    "SD1": "0.4",
    "SMS": "0.9",
    "SM1": "0.5",
    "對應鄉鎮": "[雲林縣] 斗南鎮、大埤鄉 [嘉義縣] 新港鄉、太保市"
  },
  {
    "斷層名稱": "梅山斷層",
    "r": "13",
    "SDS": "0.7",
    "SD1": "0.4",
    "SMS": "0.9",
    "SM1": "0.5",
    "對應鄉鎮": "[雲林縣] 斗南鎮、大埤鄉 [嘉義縣] 新港鄉、太保市"
  },
  {
    "斷層名稱": "梅山斷層",
    "r": ">=14",
    "SDS": "0.7",
    "SD1": "0.4",
    "SMS": "0.9",
    "SM1": "0.5",
    "對應鄉鎮": "[雲林縣] 斗南鎮、大埤鄉 [嘉義縣] 新港鄉、太保市"
  },
  {
    "斷層名稱": "大尖山斷層",
    "r": "<=1",
    "SDS": "0.92",
    "SD1": "0.52",
    "SMS": "1.21",
    "SM1": "0.78",
    "對應鄉鎮": "[南投縣] 竹山鎮、鹿谷鄉 [雲林縣] 斗六市、林內鄉、古坑鄉 [嘉義縣] 大林鎮、民雄鄉、中埔鄉、竹崎鄉、梅山鄉、番路鄉、大埔鄉 [臺南市] 白河區、東山區"
  },
  {
    "斷層名稱": "大尖山斷層",
    "r": "3",
    "SDS": "0.88",
    "SD1": "0.5",
    "SMS": "1.18",
    "SM1": "0.75",
    "對應鄉鎮": "[南投縣] 竹山鎮、鹿谷鄉 [雲林縣] 斗六市、林內鄉、古坑鄉 [嘉義縣] 大林鎮、民雄鄉、中埔鄉、竹崎鄉、梅山鄉、番路鄉、大埔鄉 [臺南市] 白河區、東山區"
  },
  {
    "斷層名稱": "大尖山斷層",
    "r": "5",
    "SDS": "0.83",
    "SD1": "0.48",
    "SMS": "1.11",
    "SM1": "0.69",
    "對應鄉鎮": "[南投縣] 竹山鎮、鹿谷鄉 [雲林縣] 斗六市、林內鄉、古坑鄉 [嘉義縣] 大林鎮、民雄鄉、中埔鄉、竹崎鄉、梅山鄉、番路鄉、大埔鄉 [臺南市] 白河區、東山區"
  },
  {
    "斷層名稱": "大尖山斷層",
    "r": "7",
    "SDS": "0.8",
    "SD1": "0.46",
    "SMS": "1.04",
    "SM1": "0.62",
    "對應鄉鎮": "[南投縣] 竹山鎮、鹿谷鄉 [雲林縣] 斗六市、林內鄉、古坑鄉 [嘉義縣] 大林鎮、民雄鄉、中埔鄉、竹崎鄉、梅山鄉、番路鄉、大埔鄉 [臺南市] 白河區、東山區"
  },
  {
    "斷層名稱": "大尖山斷層",
    "r": "9",
    "SDS": "0.8",
    "SD1": "0.45",
    "SMS": "1",
    "SM1": "0.55",
    "對應鄉鎮": "[南投縣] 竹山鎮、鹿谷鄉 [雲林縣] 斗六市、林內鄉、古坑鄉 [嘉義縣] 大林鎮、民雄鄉、中埔鄉、竹崎鄉、梅山鄉、番路鄉、大埔鄉 [臺南市] 白河區、東山區"
  },
  {
    "斷層名稱": "大尖山斷層",
    "r": "11",
    "SDS": "0.8",
    "SD1": "0.45",
    "SMS": "1",
    "SM1": "0.55",
    "對應鄉鎮": "[南投縣] 竹山鎮、鹿谷鄉 [雲林縣] 斗六市、林內鄉、古坑鄉 [嘉義縣] 大林鎮、民雄鄉、中埔鄉、竹崎鄉、梅山鄉、番路鄉、大埔鄉 [臺南市] 白河區、東山區"
  },
  {
    "斷層名稱": "大尖山斷層",
    "r": "13",
    "SDS": "0.8",
    "SD1": "0.45",
    "SMS": "1",
    "SM1": "0.55",
    "對應鄉鎮": "[南投縣] 竹山鎮、鹿谷鄉 [雲林縣] 斗六市、林內鄉、古坑鄉 [嘉義縣] 大林鎮、民雄鄉、中埔鄉、竹崎鄉、梅山鄉、番路鄉、大埔鄉 [臺南市] 白河區、東山區"
  },
  {
    "斷層名稱": "大尖山斷層",
    "r": ">=14",
    "SDS": "0.8",
    "SD1": "0.45",
    "SMS": "1",
    "SM1": "0.55",
    "對應鄉鎮": "[南投縣] 竹山鎮、鹿谷鄉 [雲林縣] 斗六市、林內鄉、古坑鄉 [嘉義縣] 大林鎮、民雄鄉、中埔鄉、竹崎鄉、梅山鄉、番路鄉、大埔鄉 [臺南市] 白河區、東山區"
  },
  {
    "斷層名稱": "大尖山斷層",
    "r": "<=1",
    "SDS": "0.92",
    "SD1": "0.52",
    "SMS": "1.21",
    "SM1": "0.78",
    "對應鄉鎮": "[嘉義縣] 水上鄉、阿里山鄉"
  },
  {
    "斷層名稱": "大尖山斷層",
    "r": "3",
    "SDS": "0.88",
    "SD1": "0.5",
    "SMS": "1.18",
    "SM1": "0.75",
    "對應鄉鎮": "[嘉義縣] 水上鄉、阿里山鄉"
  },
  {
    "斷層名稱": "大尖山斷層",
    "r": "5",
    "SDS": "0.83",
    "SD1": "0.48",
    "SMS": "1.11",
    "SM1": "0.69",
    "對應鄉鎮": "[嘉義縣] 水上鄉、阿里山鄉"
  },
  {
    "斷層名稱": "大尖山斷層",
    "r": "7",
    "SDS": "0.8",
    "SD1": "0.46",
    "SMS": "1.04",
    "SM1": "0.62",
    "對應鄉鎮": "[嘉義縣] 水上鄉、阿里山鄉"
  },
  {
    "斷層名稱": "大尖山斷層",
    "r": "9",
    "SDS": "0.7",
    "SD1": "0.4",
    "SMS": "0.9",
    "SM1": "0.5",
    "對應鄉鎮": "[嘉義縣] 水上鄉、阿里山鄉"
  },
  {
    "斷層名稱": "大尖山斷層",
    "r": "11",
    "SDS": "0.7",
    "SD1": "0.4",
    "SMS": "0.9",
    "SM1": "0.5",
    "對應鄉鎮": "[嘉義縣] 水上鄉、阿里山鄉"
  },
  {
    "斷層名稱": "大尖山斷層",
    "r": "13",
    "SDS": "0.7",
    "SD1": "0.4",
    "SMS": "0.9",
    "SM1": "0.5",
    "對應鄉鎮": "[嘉義縣] 水上鄉、阿里山鄉"
  },
  {
    "斷層名稱": "大尖山斷層",
    "r": ">=14",
    "SDS": "0.7",
    "SD1": "0.4",
    "SMS": "0.9",
    "SM1": "0.5",
    "對應鄉鎮": "[嘉義縣] 水上鄉、阿里山鄉"
  },
  {
    "斷層名稱": "觸口斷層",
    "r": "<=1",
    "SDS": "0.92",
    "SD1": "0.52",
    "SMS": "1.21",
    "SM1": "0.78",
    "對應鄉鎮": "[南投縣] 竹山鎮、鹿谷鄉 [雲林縣] 斗六市、林內鄉、古坑鄉 [嘉義縣] 大林鎮、民雄鄉、中埔鄉、竹崎鄉、梅山鄉、番路鄉、大埔鄉 [臺南市] 白河區、東山區"
  },
  {
    "斷層名稱": "觸口斷層",
    "r": "3",
    "SDS": "0.88",
    "SD1": "0.5",
    "SMS": "1.18",
    "SM1": "0.75",
    "對應鄉鎮": "[南投縣] 竹山鎮、鹿谷鄉 [雲林縣] 斗六市、林內鄉、古坑鄉 [嘉義縣] 大林鎮、民雄鄉、中埔鄉、竹崎鄉、梅山鄉、番路鄉、大埔鄉 [臺南市] 白河區、東山區"
  },
  {
    "斷層名稱": "觸口斷層",
    "r": "5",
    "SDS": "0.83",
    "SD1": "0.48",
    "SMS": "1.11",
    "SM1": "0.69",
    "對應鄉鎮": "[南投縣] 竹山鎮、鹿谷鄉 [雲林縣] 斗六市、林內鄉、古坑鄉 [嘉義縣] 大林鎮、民雄鄉、中埔鄉、竹崎鄉、梅山鄉、番路鄉、大埔鄉 [臺南市] 白河區、東山區"
  },
  {
    "斷層名稱": "觸口斷層",
    "r": "7",
    "SDS": "0.8",
    "SD1": "0.46",
    "SMS": "1.04",
    "SM1": "0.62",
    "對應鄉鎮": "[南投縣] 竹山鎮、鹿谷鄉 [雲林縣] 斗六市、林內鄉、古坑鄉 [嘉義縣] 大林鎮、民雄鄉、中埔鄉、竹崎鄉、梅山鄉、番路鄉、大埔鄉 [臺南市] 白河區、東山區"
  },
  {
    "斷層名稱": "觸口斷層",
    "r": "9",
    "SDS": "0.8",
    "SD1": "0.45",
    "SMS": "1",
    "SM1": "0.55",
    "對應鄉鎮": "[南投縣] 竹山鎮、鹿谷鄉 [雲林縣] 斗六市、林內鄉、古坑鄉 [嘉義縣] 大林鎮、民雄鄉、中埔鄉、竹崎鄉、梅山鄉、番路鄉、大埔鄉 [臺南市] 白河區、東山區"
  },
  {
    "斷層名稱": "觸口斷層",
    "r": "11",
    "SDS": "0.8",
    "SD1": "0.45",
    "SMS": "1",
    "SM1": "0.55",
    "對應鄉鎮": "[南投縣] 竹山鎮、鹿谷鄉 [雲林縣] 斗六市、林內鄉、古坑鄉 [嘉義縣] 大林鎮、民雄鄉、中埔鄉、竹崎鄉、梅山鄉、番路鄉、大埔鄉 [臺南市] 白河區、東山區"
  },
  {
    "斷層名稱": "觸口斷層",
    "r": "13",
    "SDS": "0.8",
    "SD1": "0.45",
    "SMS": "1",
    "SM1": "0.55",
    "對應鄉鎮": "[南投縣] 竹山鎮、鹿谷鄉 [雲林縣] 斗六市、林內鄉、古坑鄉 [嘉義縣] 大林鎮、民雄鄉、中埔鄉、竹崎鄉、梅山鄉、番路鄉、大埔鄉 [臺南市] 白河區、東山區"
  },
  {
    "斷層名稱": "觸口斷層",
    "r": ">=14",
    "SDS": "0.8",
    "SD1": "0.45",
    "SMS": "1",
    "SM1": "0.55",
    "對應鄉鎮": "[南投縣] 竹山鎮、鹿谷鄉 [雲林縣] 斗六市、林內鄉、古坑鄉 [嘉義縣] 大林鎮、民雄鄉、中埔鄉、竹崎鄉、梅山鄉、番路鄉、大埔鄉 [臺南市] 白河區、東山區"
  },
  {
    "斷層名稱": "觸口斷層",
    "r": "<=1",
    "SDS": "0.92",
    "SD1": "0.52",
    "SMS": "1.21",
    "SM1": "0.78",
    "對應鄉鎮": "[嘉義縣] 水上鄉、阿里山鄉"
  },
  {
    "斷層名稱": "觸口斷層",
    "r": "3",
    "SDS": "0.88",
    "SD1": "0.5",
    "SMS": "1.18",
    "SM1": "0.75",
    "對應鄉鎮": "[嘉義縣] 水上鄉、阿里山鄉"
  },
  {
    "斷層名稱": "觸口斷層",
    "r": "5",
    "SDS": "0.83",
    "SD1": "0.48",
    "SMS": "1.11",
    "SM1": "0.69",
    "對應鄉鎮": "[嘉義縣] 水上鄉、阿里山鄉"
  },
  {
    "斷層名稱": "觸口斷層",
    "r": "7",
    "SDS": "0.8",
    "SD1": "0.46",
    "SMS": "1.04",
    "SM1": "0.62",
    "對應鄉鎮": "[嘉義縣] 水上鄉、阿里山鄉"
  },
  {
    "斷層名稱": "觸口斷層",
    "r": "9",
    "SDS": "0.7",
    "SD1": "0.4",
    "SMS": "0.9",
    "SM1": "0.5",
    "對應鄉鎮": "[嘉義縣] 水上鄉、阿里山鄉"
  },
  {
    "斷層名稱": "觸口斷層",
    "r": "11",
    "SDS": "0.7",
    "SD1": "0.4",
    "SMS": "0.9",
    "SM1": "0.5",
    "對應鄉鎮": "[嘉義縣] 水上鄉、阿里山鄉"
  },
  {
    "斷層名稱": "觸口斷層",
    "r": "13",
    "SDS": "0.7",
    "SD1": "0.4",
    "SMS": "0.9",
    "SM1": "0.5",
    "對應鄉鎮": "[嘉義縣] 水上鄉、阿里山鄉"
  },
  {
    "斷層名稱": "觸口斷層",
    "r": ">=14",
    "SDS": "0.7",
    "SD1": "0.4",
    "SMS": "0.9",
    "SM1": "0.5",
    "對應鄉鎮": "[嘉義縣] 水上鄉、阿里山鄉"
  },
  {
    "斷層名稱": "六甲斷層",
    "r": "<=1",
    "SDS": "0.88",
    "SD1": "0.52",
    "SMS": "1.1",
    "SM1": "0.69",
    "對應鄉鎮": "[臺南市] 白河區、柳營區、東山區、六甲區、官田區"
  },
  {
    "斷層名稱": "六甲斷層",
    "r": "3",
    "SDS": "0.84",
    "SD1": "0.5",
    "SMS": "1.05",
    "SM1": "0.61",
    "對應鄉鎮": "[臺南市] 白河區、柳營區、東山區、六甲區、官田區"
  },
  {
    "斷層名稱": "六甲斷層",
    "r": "5",
    "SDS": "0.8",
    "SD1": "0.45",
    "SMS": "1",
    "SM1": "0.55",
    "對應鄉鎮": "[臺南市] 白河區、柳營區、東山區、六甲區、官田區"
  },
  {
    "斷層名稱": "六甲斷層",
    "r": "7",
    "SDS": "0.8",
    "SD1": "0.45",
    "SMS": "1",
    "SM1": "0.55",
    "對應鄉鎮": "[臺南市] 白河區、柳營區、東山區、六甲區、官田區"
  },
  {
    "斷層名稱": "六甲斷層",
    "r": "9",
    "SDS": "0.8",
    "SD1": "0.45",
    "SMS": "1",
    "SM1": "0.55",
    "對應鄉鎮": "[臺南市] 白河區、柳營區、東山區、六甲區、官田區"
  },
  {
    "斷層名稱": "六甲斷層",
    "r": "11",
    "SDS": "0.8",
    "SD1": "0.45",
    "SMS": "1",
    "SM1": "0.55",
    "對應鄉鎮": "[臺南市] 白河區、柳營區、東山區、六甲區、官田區"
  },
  {
    "斷層名稱": "六甲斷層",
    "r": "13",
    "SDS": "0.8",
    "SD1": "0.45",
    "SMS": "1",
    "SM1": "0.55",
    "對應鄉鎮": "[臺南市] 白河區、柳營區、東山區、六甲區、官田區"
  },
  {
    "斷層名稱": "六甲斷層",
    "r": ">=14",
    "SDS": "0.8",
    "SD1": "0.45",
    "SMS": "1",
    "SM1": "0.55",
    "對應鄉鎮": "[臺南市] 白河區、柳營區、東山區、六甲區、官田區"
  },
  {
    "斷層名稱": "新化斷層",
    "r": "<=1",
    "SDS": "0.98",
    "SD1": "0.52",
    "SMS": "1.29",
    "SM1": "0.72",
    "對應鄉鎮": "[臺南市] 新化區、新市區、山上區、左鎮區、永康區"
  },
  {
    "斷層名稱": "新化斷層",
    "r": "3",
    "SDS": "0.88",
    "SD1": "0.48",
    "SMS": "1.14",
    "SM1": "0.65",
    "對應鄉鎮": "[臺南市] 新化區、新市區、山上區、左鎮區、永康區"
  },
  {
    "斷層名稱": "新化斷層",
    "r": "5",
    "SDS": "0.82",
    "SD1": "0.46",
    "SMS": "1.05",
    "SM1": "0.59",
    "對應鄉鎮": "[臺南市] 新化區、新市區、山上區、左鎮區、永康區"
  },
  {
    "斷層名稱": "新化斷層",
    "r": "7",
    "SDS": "0.8",
    "SD1": "0.45",
    "SMS": "1",
    "SM1": "0.55",
    "對應鄉鎮": "[臺南市] 新化區、新市區、山上區、左鎮區、永康區"
  },
  {
    "斷層名稱": "新化斷層",
    "r": "9",
    "SDS": "0.8",
    "SD1": "0.45",
    "SMS": "1",
    "SM1": "0.55",
    "對應鄉鎮": "[臺南市] 新化區、新市區、山上區、左鎮區、永康區"
  },
  {
    "斷層名稱": "新化斷層",
    "r": "11",
    "SDS": "0.8",
    "SD1": "0.45",
    "SMS": "1",
    "SM1": "0.55",
    "對應鄉鎮": "[臺南市] 新化區、新市區、山上區、左鎮區、永康區"
  },
  {
    "斷層名稱": "新化斷層",
    "r": "13",
    "SDS": "0.8",
    "SD1": "0.45",
    "SMS": "1",
    "SM1": "0.55",
    "對應鄉鎮": "[臺南市] 新化區、新市區、山上區、左鎮區、永康區"
  },
  {
    "斷層名稱": "新化斷層",
    "r": ">=14",
    "SDS": "0.8",
    "SD1": "0.45",
    "SMS": "1",
    "SM1": "0.55",
    "對應鄉鎮": "[臺南市] 新化區、新市區、山上區、左鎮區、永康區"
  },
  {
    "斷層名稱": "新化斷層",
    "r": "<=1",
    "SDS": "0.98",
    "SD1": "0.52",
    "SMS": "1.29",
    "SM1": "0.72",
    "對應鄉鎮": "[臺南市] 大內區、善化區、歸仁區、關廟區"
  },
  {
    "斷層名稱": "新化斷層",
    "r": "3",
    "SDS": "0.88",
    "SD1": "0.48",
    "SMS": "1.14",
    "SM1": "0.65",
    "對應鄉鎮": "[臺南市] 大內區、善化區、歸仁區、關廟區"
  },
  {
    "斷層名稱": "新化斷層",
    "r": "5",
    "SDS": "0.82",
    "SD1": "0.46",
    "SMS": "1.05",
    "SM1": "0.59",
    "對應鄉鎮": "[臺南市] 大內區、善化區、歸仁區、關廟區"
  },
  {
    "斷層名稱": "新化斷層",
    "r": "7",
    "SDS": "0.7",
    "SD1": "0.4",
    "SMS": "0.9",
    "SM1": "0.5",
    "對應鄉鎮": "[臺南市] 大內區、善化區、歸仁區、關廟區"
  },
  {
    "斷層名稱": "新化斷層",
    "r": "9",
    "SDS": "0.7",
    "SD1": "0.4",
    "SMS": "0.9",
    "SM1": "0.5",
    "對應鄉鎮": "[臺南市] 大內區、善化區、歸仁區、關廟區"
  },
  {
    "斷層名稱": "新化斷層",
    "r": "11",
    "SDS": "0.7",
    "SD1": "0.4",
    "SMS": "0.9",
    "SM1": "0.5",
    "對應鄉鎮": "[臺南市] 大內區、善化區、歸仁區、關廟區"
  },
  {
    "斷層名稱": "新化斷層",
    "r": "13",
    "SDS": "0.7",
    "SD1": "0.4",
    "SMS": "0.9",
    "SM1": "0.5",
    "對應鄉鎮": "[臺南市] 大內區、善化區、歸仁區、關廟區"
  },
  {
    "斷層名稱": "新化斷層",
    "r": ">=14",
    "SDS": "0.7",
    "SD1": "0.4",
    "SMS": "0.9",
    "SM1": "0.5",
    "對應鄉鎮": "[臺南市] 大內區、善化區、歸仁區、關廟區"
  },
  {
    "斷層名稱": "旗山斷層",
    "r": "<=1",
    "SDS": "0.92",
    "SD1": "0.54",
    "SMS": "1.2",
    "SM1": "0.74",
    "對應鄉鎮": "[高雄市] 楠梓區、大社區、仁武區、橋頭區、燕巢區、田寮區、旗山區"
  },
  {
    "斷層名稱": "旗山斷層",
    "r": "3",
    "SDS": "0.88",
    "SD1": "0.5",
    "SMS": "1.1",
    "SM1": "0.66",
    "對應鄉鎮": "[高雄市] 楠梓區、大社區、仁武區、橋頭區、燕巢區、田寮區、旗山區"
  },
  {
    "斷層名稱": "旗山斷層",
    "r": "5",
    "SDS": "0.84",
    "SD1": "0.47",
    "SMS": "1.05",
    "SM1": "0.61",
    "對應鄉鎮": "[高雄市] 楠梓區、大社區、仁武區、橋頭區、燕巢區、田寮區、旗山區"
  },
  {
    "斷層名稱": "旗山斷層",
    "r": "7",
    "SDS": "0.8",
    "SD1": "0.45",
    "SMS": "1",
    "SM1": "0.55",
    "對應鄉鎮": "[高雄市] 楠梓區、大社區、仁武區、橋頭區、燕巢區、田寮區、旗山區"
  },
  {
    "斷層名稱": "旗山斷層",
    "r": "9",
    "SDS": "0.8",
    "SD1": "0.45",
    "SMS": "1",
    "SM1": "0.55",
    "對應鄉鎮": "[高雄市] 楠梓區、大社區、仁武區、橋頭區、燕巢區、田寮區、旗山區"
  },
  {
    "斷層名稱": "旗山斷層",
    "r": "11",
    "SDS": "0.8",
    "SD1": "0.45",
    "SMS": "1",
    "SM1": "0.55",
    "對應鄉鎮": "[高雄市] 楠梓區、大社區、仁武區、橋頭區、燕巢區、田寮區、旗山區"
  },
  {
    "斷層名稱": "旗山斷層",
    "r": "13",
    "SDS": "0.8",
    "SD1": "0.45",
    "SMS": "1",
    "SM1": "0.55",
    "對應鄉鎮": "[高雄市] 楠梓區、大社區、仁武區、橋頭區、燕巢區、田寮區、旗山區"
  },
  {
    "斷層名稱": "旗山斷層",
    "r": ">=14",
    "SDS": "0.8",
    "SD1": "0.45",
    "SMS": "1",
    "SM1": "0.55",
    "對應鄉鎮": "[高雄市] 楠梓區、大社區、仁武區、橋頭區、燕巢區、田寮區、旗山區"
  },
  {
    "斷層名稱": "旗山斷層",
    "r": "<=1",
    "SDS": "0.92",
    "SD1": "0.54",
    "SMS": "1.2",
    "SM1": "0.74",
    "對應鄉鎮": "[高雄市] 左營區、三民區、大樹區、鳥松區、岡山區、美濃區、杉林區、內門區 [屏東縣] 里港鄉"
  },
  {
    "斷層名稱": "旗山斷層",
    "r": "3",
    "SDS": "0.88",
    "SD1": "0.5",
    "SMS": "1.1",
    "SM1": "0.66",
    "對應鄉鎮": "[高雄市] 左營區、三民區、大樹區、鳥松區、岡山區、美濃區、杉林區、內門區 [屏東縣] 里港鄉"
  },
  {
    "斷層名稱": "旗山斷層",
    "r": "5",
    "SDS": "0.84",
    "SD1": "0.47",
    "SMS": "1.05",
    "SM1": "0.61",
    "對應鄉鎮": "[高雄市] 左營區、三民區、大樹區、鳥松區、岡山區、美濃區、杉林區、內門區 [屏東縣] 里港鄉"
  },
  {
    "斷層名稱": "旗山斷層",
    "r": "7",
    "SDS": "0.7",
    "SD1": "0.4",
    "SMS": "0.9",
    "SM1": "0.5",
    "對應鄉鎮": "[高雄市] 左營區、三民區、大樹區、鳥松區、岡山區、美濃區、杉林區、內門區 [屏東縣] 里港鄉"
  },
  {
    "斷層名稱": "旗山斷層",
    "r": "9",
    "SDS": "0.7",
    "SD1": "0.4",
    "SMS": "0.9",
    "SM1": "0.5",
    "對應鄉鎮": "[高雄市] 左營區、三民區、大樹區、鳥松區、岡山區、美濃區、杉林區、內門區 [屏東縣] 里港鄉"
  },
  {
    "斷層名稱": "旗山斷層",
    "r": "11",
    "SDS": "0.7",
    "SD1": "0.4",
    "SMS": "0.9",
    "SM1": "0.5",
    "對應鄉鎮": "[高雄市] 左營區、三民區、大樹區、鳥松區、岡山區、美濃區、杉林區、內門區 [屏東縣] 里港鄉"
  },
  {
    "斷層名稱": "旗山斷層",
    "r": "13",
    "SDS": "0.7",
    "SD1": "0.4",
    "SMS": "0.9",
    "SM1": "0.5",
    "對應鄉鎮": "[高雄市] 左營區、三民區、大樹區、鳥松區、岡山區、美濃區、杉林區、內門區 [屏東縣] 里港鄉"
  },
  {
    "斷層名稱": "旗山斷層",
    "r": ">=14",
    "SDS": "0.7",
    "SD1": "0.4",
    "SMS": "0.9",
    "SM1": "0.5",
    "對應鄉鎮": "[高雄市] 左營區、三民區、大樹區、鳥松區、岡山區、美濃區、杉林區、內門區 [屏東縣] 里港鄉"
  },
  {
    "斷層名稱": "米崙斷層",
    "r": "<=1",
    "SDS": "1.14",
    "SD1": "0.71",
    "SMS": "1.32",
    "SM1": "0.87",
    "對應鄉鎮": "[花蓮縣] 花蓮市、鳳林鎮、玉里鎮、新城鄉、吉安鄉、壽豐鄉、光復鄉、豐濱鄉、瑞穗鄉、富里鄉、秀林鄉、萬榮鄉、卓溪鄉 [臺東縣] 臺東市、成功鎮、關山鎮、卑南鄉、東河鄉、長濱鄉、鹿野鄉、池上鄉、延平鄉、海端鄉"
  },
  {
    "斷層名稱": "米崙斷層",
    "r": "3",
    "SDS": "1.1",
    "SD1": "0.69",
    "SMS": "1.27",
    "SM1": "0.83",
    "對應鄉鎮": "[花蓮縣] 花蓮市、鳳林鎮、玉里鎮、新城鄉、吉安鄉、壽豐鄉、光復鄉、豐濱鄉、瑞穗鄉、富里鄉、秀林鄉、萬榮鄉、卓溪鄉 [臺東縣] 臺東市、成功鎮、關山鎮、卑南鄉、東河鄉、長濱鄉、鹿野鄉、池上鄉、延平鄉、海端鄉"
  },
  {
    "斷層名稱": "米崙斷層",
    "r": "5",
    "SDS": "1.06",
    "SD1": "0.65",
    "SMS": "1.18",
    "SM1": "0.76",
    "對應鄉鎮": "[花蓮縣] 花蓮市、鳳林鎮、玉里鎮、新城鄉、吉安鄉、壽豐鄉、光復鄉、豐濱鄉、瑞穗鄉、富里鄉、秀林鄉、萬榮鄉、卓溪鄉 [臺東縣] 臺東市、成功鎮、關山鎮、卑南鄉、東河鄉、長濱鄉、鹿野鄉、池上鄉、延平鄉、海端鄉"
  },
  {
    "斷層名稱": "米崙斷層",
    "r": "7",
    "SDS": "1.01",
    "SD1": "0.61",
    "SMS": "1.09",
    "SM1": "0.7",
    "對應鄉鎮": "[花蓮縣] 花蓮市、鳳林鎮、玉里鎮、新城鄉、吉安鄉、壽豐鄉、光復鄉、豐濱鄉、瑞穗鄉、富里鄉、秀林鄉、萬榮鄉、卓溪鄉 [臺東縣] 臺東市、成功鎮、關山鎮、卑南鄉、東河鄉、長濱鄉、鹿野鄉、池上鄉、延平鄉、海端鄉"
  },
  {
    "斷層名稱": "米崙斷層",
    "r": "9",
    "SDS": "0.94",
    "SD1": "0.56",
    "SMS": "1.04",
    "SM1": "0.66",
    "對應鄉鎮": "[花蓮縣] 花蓮市、鳳林鎮、玉里鎮、新城鄉、吉安鄉、壽豐鄉、光復鄉、豐濱鄉、瑞穗鄉、富里鄉、秀林鄉、萬榮鄉、卓溪鄉 [臺東縣] 臺東市、成功鎮、關山鎮、卑南鄉、東河鄉、長濱鄉、鹿野鄉、池上鄉、延平鄉、海端鄉"
  },
  {
    "斷層名稱": "米崙斷層",
    "r": "11",
    "SDS": "0.87",
    "SD1": "0.51",
    "SMS": "1.01",
    "SM1": "0.61",
    "對應鄉鎮": "[花蓮縣] 花蓮市、鳳林鎮、玉里鎮、新城鄉、吉安鄉、壽豐鄉、光復鄉、豐濱鄉、瑞穗鄉、富里鄉、秀林鄉、萬榮鄉、卓溪鄉 [臺東縣] 臺東市、成功鎮、關山鎮、卑南鄉、東河鄉、長濱鄉、鹿野鄉、池上鄉、延平鄉、海端鄉"
  },
  {
    "斷層名稱": "米崙斷層",
    "r": "13",
    "SDS": "0.8",
    "SD1": "0.45",
    "SMS": "1",
    "SM1": "0.55",
    "對應鄉鎮": "[花蓮縣] 花蓮市、鳳林鎮、玉里鎮、新城鄉、吉安鄉、壽豐鄉、光復鄉、豐濱鄉、瑞穗鄉、富里鄉、秀林鄉、萬榮鄉、卓溪鄉 [臺東縣] 臺東市、成功鎮、關山鎮、卑南鄉、東河鄉、長濱鄉、鹿野鄉、池上鄉、延平鄉、海端鄉"
  },
  {
    "斷層名稱": "米崙斷層",
    "r": ">=14",
    "SDS": "0.8",
    "SD1": "0.45",
    "SMS": "1",
    "SM1": "0.55",
    "對應鄉鎮": "[花蓮縣] 花蓮市、鳳林鎮、玉里鎮、新城鄉、吉安鄉、壽豐鄉、光復鄉、豐濱鄉、瑞穗鄉、富里鄉、秀林鄉、萬榮鄉、卓溪鄉 [臺東縣] 臺東市、成功鎮、關山鎮、卑南鄉、東河鄉、長濱鄉、鹿野鄉、池上鄉、延平鄉、海端鄉"
  },
  {
    "斷層名稱": "嶺頂斷層",
    "r": "<=1",
    "SDS": "1.14",
    "SD1": "0.71",
    "SMS": "1.32",
    "SM1": "0.87",
    "對應鄉鎮": "[花蓮縣] 花蓮市、鳳林鎮、玉里鎮、新城鄉、吉安鄉、壽豐鄉、光復鄉、豐濱鄉、瑞穗鄉、富里鄉、秀林鄉、萬榮鄉、卓溪鄉 [臺東縣] 臺東市、成功鎮、關山鎮、卑南鄉、東河鄉、長濱鄉、鹿野鄉、池上鄉、延平鄉、海端鄉"
  },
  {
    "斷層名稱": "嶺頂斷層",
    "r": "3",
    "SDS": "1.1",
    "SD1": "0.69",
    "SMS": "1.27",
    "SM1": "0.83",
    "對應鄉鎮": "[花蓮縣] 花蓮市、鳳林鎮、玉里鎮、新城鄉、吉安鄉、壽豐鄉、光復鄉、豐濱鄉、瑞穗鄉、富里鄉、秀林鄉、萬榮鄉、卓溪鄉 [臺東縣] 臺東市、成功鎮、關山鎮、卑南鄉、東河鄉、長濱鄉、鹿野鄉、池上鄉、延平鄉、海端鄉"
  },
  {
    "斷層名稱": "嶺頂斷層",
    "r": "5",
    "SDS": "1.06",
    "SD1": "0.65",
    "SMS": "1.18",
    "SM1": "0.76",
    "對應鄉鎮": "[花蓮縣] 花蓮市、鳳林鎮、玉里鎮、新城鄉、吉安鄉、壽豐鄉、光復鄉、豐濱鄉、瑞穗鄉、富里鄉、秀林鄉、萬榮鄉、卓溪鄉 [臺東縣] 臺東市、成功鎮、關山鎮、卑南鄉、東河鄉、長濱鄉、鹿野鄉、池上鄉、延平鄉、海端鄉"
  },
  {
    "斷層名稱": "嶺頂斷層",
    "r": "7",
    "SDS": "1.01",
    "SD1": "0.61",
    "SMS": "1.09",
    "SM1": "0.7",
    "對應鄉鎮": "[花蓮縣] 花蓮市、鳳林鎮、玉里鎮、新城鄉、吉安鄉、壽豐鄉、光復鄉、豐濱鄉、瑞穗鄉、富里鄉、秀林鄉、萬榮鄉、卓溪鄉 [臺東縣] 臺東市、成功鎮、關山鎮、卑南鄉、東河鄉、長濱鄉、鹿野鄉、池上鄉、延平鄉、海端鄉"
  },
  {
    "斷層名稱": "嶺頂斷層",
    "r": "9",
    "SDS": "0.94",
    "SD1": "0.56",
    "SMS": "1.04",
    "SM1": "0.66",
    "對應鄉鎮": "[花蓮縣] 花蓮市、鳳林鎮、玉里鎮、新城鄉、吉安鄉、壽豐鄉、光復鄉、豐濱鄉、瑞穗鄉、富里鄉、秀林鄉、萬榮鄉、卓溪鄉 [臺東縣] 臺東市、成功鎮、關山鎮、卑南鄉、東河鄉、長濱鄉、鹿野鄉、池上鄉、延平鄉、海端鄉"
  },
  {
    "斷層名稱": "嶺頂斷層",
    "r": "11",
    "SDS": "0.87",
    "SD1": "0.51",
    "SMS": "1.01",
    "SM1": "0.61",
    "對應鄉鎮": "[花蓮縣] 花蓮市、鳳林鎮、玉里鎮、新城鄉、吉安鄉、壽豐鄉、光復鄉、豐濱鄉、瑞穗鄉、富里鄉、秀林鄉、萬榮鄉、卓溪鄉 [臺東縣] 臺東市、成功鎮、關山鎮、卑南鄉、東河鄉、長濱鄉、鹿野鄉、池上鄉、延平鄉、海端鄉"
  },
  {
    "斷層名稱": "嶺頂斷層",
    "r": "13",
    "SDS": "0.8",
    "SD1": "0.45",
    "SMS": "1",
    "SM1": "0.55",
    "對應鄉鎮": "[花蓮縣] 花蓮市、鳳林鎮、玉里鎮、新城鄉、吉安鄉、壽豐鄉、光復鄉、豐濱鄉、瑞穗鄉、富里鄉、秀林鄉、萬榮鄉、卓溪鄉 [臺東縣] 臺東市、成功鎮、關山鎮、卑南鄉、東河鄉、長濱鄉、鹿野鄉、池上鄉、延平鄉、海端鄉"
  },
  {
    "斷層名稱": "嶺頂斷層",
    "r": ">=14",
    "SDS": "0.8",
    "SD1": "0.45",
    "SMS": "1",
    "SM1": "0.55",
    "對應鄉鎮": "[花蓮縣] 花蓮市、鳳林鎮、玉里鎮、新城鄉、吉安鄉、壽豐鄉、光復鄉、豐濱鄉、瑞穗鄉、富里鄉、秀林鄉、萬榮鄉、卓溪鄉 [臺東縣] 臺東市、成功鎮、關山鎮、卑南鄉、東河鄉、長濱鄉、鹿野鄉、池上鄉、延平鄉、海端鄉"
  },
  {
    "斷層名稱": "瑞穗斷層",
    "r": "<=1",
    "SDS": "1.14",
    "SD1": "0.71",
    "SMS": "1.32",
    "SM1": "0.87",
    "對應鄉鎮": "[花蓮縣] 花蓮市、鳳林鎮、玉里鎮、新城鄉、吉安鄉、壽豐鄉、光復鄉、豐濱鄉、瑞穗鄉、富里鄉、秀林鄉、萬榮鄉、卓溪鄉 [臺東縣] 臺東市、成功鎮、關山鎮、卑南鄉、東河鄉、長濱鄉、鹿野鄉、池上鄉、延平鄉、海端鄉"
  },
  {
    "斷層名稱": "瑞穗斷層",
    "r": "3",
    "SDS": "1.1",
    "SD1": "0.69",
    "SMS": "1.27",
    "SM1": "0.83",
    "對應鄉鎮": "[花蓮縣] 花蓮市、鳳林鎮、玉里鎮、新城鄉、吉安鄉、壽豐鄉、光復鄉、豐濱鄉、瑞穗鄉、富里鄉、秀林鄉、萬榮鄉、卓溪鄉 [臺東縣] 臺東市、成功鎮、關山鎮、卑南鄉、東河鄉、長濱鄉、鹿野鄉、池上鄉、延平鄉、海端鄉"
  },
  {
    "斷層名稱": "瑞穗斷層",
    "r": "5",
    "SDS": "1.06",
    "SD1": "0.65",
    "SMS": "1.18",
    "SM1": "0.76",
    "對應鄉鎮": "[花蓮縣] 花蓮市、鳳林鎮、玉里鎮、新城鄉、吉安鄉、壽豐鄉、光復鄉、豐濱鄉、瑞穗鄉、富里鄉、秀林鄉、萬榮鄉、卓溪鄉 [臺東縣] 臺東市、成功鎮、關山鎮、卑南鄉、東河鄉、長濱鄉、鹿野鄉、池上鄉、延平鄉、海端鄉"
  },
  {
    "斷層名稱": "瑞穗斷層",
    "r": "7",
    "SDS": "1.01",
    "SD1": "0.61",
    "SMS": "1.09",
    "SM1": "0.7",
    "對應鄉鎮": "[花蓮縣] 花蓮市、鳳林鎮、玉里鎮、新城鄉、吉安鄉、壽豐鄉、光復鄉、豐濱鄉、瑞穗鄉、富里鄉、秀林鄉、萬榮鄉、卓溪鄉 [臺東縣] 臺東市、成功鎮、關山鎮、卑南鄉、東河鄉、長濱鄉、鹿野鄉、池上鄉、延平鄉、海端鄉"
  },
  {
    "斷層名稱": "瑞穗斷層",
    "r": "9",
    "SDS": "0.94",
    "SD1": "0.56",
    "SMS": "1.04",
    "SM1": "0.66",
    "對應鄉鎮": "[花蓮縣] 花蓮市、鳳林鎮、玉里鎮、新城鄉、吉安鄉、壽豐鄉、光復鄉、豐濱鄉、瑞穗鄉、富里鄉、秀林鄉、萬榮鄉、卓溪鄉 [臺東縣] 臺東市、成功鎮、關山鎮、卑南鄉、東河鄉、長濱鄉、鹿野鄉、池上鄉、延平鄉、海端鄉"
  },
  {
    "斷層名稱": "瑞穗斷層",
    "r": "11",
    "SDS": "0.87",
    "SD1": "0.51",
    "SMS": "1.01",
    "SM1": "0.61",
    "對應鄉鎮": "[花蓮縣] 花蓮市、鳳林鎮、玉里鎮、新城鄉、吉安鄉、壽豐鄉、光復鄉、豐濱鄉、瑞穗鄉、富里鄉、秀林鄉、萬榮鄉、卓溪鄉 [臺東縣] 臺東市、成功鎮、關山鎮、卑南鄉、東河鄉、長濱鄉、鹿野鄉、池上鄉、延平鄉、海端鄉"
  },
  {
    "斷層名稱": "瑞穗斷層",
    "r": "13",
    "SDS": "0.8",
    "SD1": "0.45",
    "SMS": "1",
    "SM1": "0.55",
    "對應鄉鎮": "[花蓮縣] 花蓮市、鳳林鎮、玉里鎮、新城鄉、吉安鄉、壽豐鄉、光復鄉、豐濱鄉、瑞穗鄉、富里鄉、秀林鄉、萬榮鄉、卓溪鄉 [臺東縣] 臺東市、成功鎮、關山鎮、卑南鄉、東河鄉、長濱鄉、鹿野鄉、池上鄉、延平鄉、海端鄉"
  },
  {
    "斷層名稱": "瑞穗斷層",
    "r": ">=14",
    "SDS": "0.8",
    "SD1": "0.45",
    "SMS": "1",
    "SM1": "0.55",
    "對應鄉鎮": "[花蓮縣] 花蓮市、鳳林鎮、玉里鎮、新城鄉、吉安鄉、壽豐鄉、光復鄉、豐濱鄉、瑞穗鄉、富里鄉、秀林鄉、萬榮鄉、卓溪鄉 [臺東縣] 臺東市、成功鎮、關山鎮、卑南鄉、東河鄉、長濱鄉、鹿野鄉、池上鄉、延平鄉、海端鄉"
  },
  {
    "斷層名稱": "玉里斷層",
    "r": "<=1",
    "SDS": "1.14",
    "SD1": "0.71",
    "SMS": "1.32",
    "SM1": "0.87",
    "對應鄉鎮": "[花蓮縣] 花蓮市、鳳林鎮、玉里鎮、新城鄉、吉安鄉、壽豐鄉、光復鄉、豐濱鄉、瑞穗鄉、富里鄉、秀林鄉、萬榮鄉、卓溪鄉 [臺東縣] 臺東市、成功鎮、關山鎮、卑南鄉、東河鄉、長濱鄉、鹿野鄉、池上鄉、延平鄉、海端鄉"
  },
  {
    "斷層名稱": "玉里斷層",
    "r": "3",
    "SDS": "1.1",
    "SD1": "0.69",
    "SMS": "1.27",
    "SM1": "0.83",
    "對應鄉鎮": "[花蓮縣] 花蓮市、鳳林鎮、玉里鎮、新城鄉、吉安鄉、壽豐鄉、光復鄉、豐濱鄉、瑞穗鄉、富里鄉、秀林鄉、萬榮鄉、卓溪鄉 [臺東縣] 臺東市、成功鎮、關山鎮、卑南鄉、東河鄉、長濱鄉、鹿野鄉、池上鄉、延平鄉、海端鄉"
  },
  {
    "斷層名稱": "玉里斷層",
    "r": "5",
    "SDS": "1.06",
    "SD1": "0.65",
    "SMS": "1.18",
    "SM1": "0.76",
    "對應鄉鎮": "[花蓮縣] 花蓮市、鳳林鎮、玉里鎮、新城鄉、吉安鄉、壽豐鄉、光復鄉、豐濱鄉、瑞穗鄉、富里鄉、秀林鄉、萬榮鄉、卓溪鄉 [臺東縣] 臺東市、成功鎮、關山鎮、卑南鄉、東河鄉、長濱鄉、鹿野鄉、池上鄉、延平鄉、海端鄉"
  },
  {
    "斷層名稱": "玉里斷層",
    "r": "7",
    "SDS": "1.01",
    "SD1": "0.61",
    "SMS": "1.09",
    "SM1": "0.7",
    "對應鄉鎮": "[花蓮縣] 花蓮市、鳳林鎮、玉里鎮、新城鄉、吉安鄉、壽豐鄉、光復鄉、豐濱鄉、瑞穗鄉、富里鄉、秀林鄉、萬榮鄉、卓溪鄉 [臺東縣] 臺東市、成功鎮、關山鎮、卑南鄉、東河鄉、長濱鄉、鹿野鄉、池上鄉、延平鄉、海端鄉"
  },
  {
    "斷層名稱": "玉里斷層",
    "r": "9",
    "SDS": "0.94",
    "SD1": "0.56",
    "SMS": "1.04",
    "SM1": "0.66",
    "對應鄉鎮": "[花蓮縣] 花蓮市、鳳林鎮、玉里鎮、新城鄉、吉安鄉、壽豐鄉、光復鄉、豐濱鄉、瑞穗鄉、富里鄉、秀林鄉、萬榮鄉、卓溪鄉 [臺東縣] 臺東市、成功鎮、關山鎮、卑南鄉、東河鄉、長濱鄉、鹿野鄉、池上鄉、延平鄉、海端鄉"
  },
  {
    "斷層名稱": "玉里斷層",
    "r": "11",
    "SDS": "0.87",
    "SD1": "0.51",
    "SMS": "1.01",
    "SM1": "0.61",
    "對應鄉鎮": "[花蓮縣] 花蓮市、鳳林鎮、玉里鎮、新城鄉、吉安鄉、壽豐鄉、光復鄉、豐濱鄉、瑞穗鄉、富里鄉、秀林鄉、萬榮鄉、卓溪鄉 [臺東縣] 臺東市、成功鎮、關山鎮、卑南鄉、東河鄉、長濱鄉、鹿野鄉、池上鄉、延平鄉、海端鄉"
  },
  {
    "斷層名稱": "玉里斷層",
    "r": "13",
    "SDS": "0.8",
    "SD1": "0.45",
    "SMS": "1",
    "SM1": "0.55",
    "對應鄉鎮": "[花蓮縣] 花蓮市、鳳林鎮、玉里鎮、新城鄉、吉安鄉、壽豐鄉、光復鄉、豐濱鄉、瑞穗鄉、富里鄉、秀林鄉、萬榮鄉、卓溪鄉 [臺東縣] 臺東市、成功鎮、關山鎮、卑南鄉、東河鄉、長濱鄉、鹿野鄉、池上鄉、延平鄉、海端鄉"
  },
  {
    "斷層名稱": "玉里斷層",
    "r": ">=14",
    "SDS": "0.8",
    "SD1": "0.45",
    "SMS": "1",
    "SM1": "0.55",
    "對應鄉鎮": "[花蓮縣] 花蓮市、鳳林鎮、玉里鎮、新城鄉、吉安鄉、壽豐鄉、光復鄉、豐濱鄉、瑞穗鄉、富里鄉、秀林鄉、萬榮鄉、卓溪鄉 [臺東縣] 臺東市、成功鎮、關山鎮、卑南鄉、東河鄉、長濱鄉、鹿野鄉、池上鄉、延平鄉、海端鄉"
  },
  {
    "斷層名稱": "池上斷層",
    "r": "<=1",
    "SDS": "1.14",
    "SD1": "0.71",
    "SMS": "1.32",
    "SM1": "0.87",
    "對應鄉鎮": "[花蓮縣] 花蓮市、鳳林鎮、玉里鎮、新城鄉、吉安鄉、壽豐鄉、光復鄉、豐濱鄉、瑞穗鄉、富里鄉、秀林鄉、萬榮鄉、卓溪鄉 [臺東縣] 臺東市、成功鎮、關山鎮、卑南鄉、東河鄉、長濱鄉、鹿野鄉、池上鄉、延平鄉、海端鄉"
  },
  {
    "斷層名稱": "池上斷層",
    "r": "3",
    "SDS": "1.1",
    "SD1": "0.69",
    "SMS": "1.27",
    "SM1": "0.83",
    "對應鄉鎮": "[花蓮縣] 花蓮市、鳳林鎮、玉里鎮、新城鄉、吉安鄉、壽豐鄉、光復鄉、豐濱鄉、瑞穗鄉、富里鄉、秀林鄉、萬榮鄉、卓溪鄉 [臺東縣] 臺東市、成功鎮、關山鎮、卑南鄉、東河鄉、長濱鄉、鹿野鄉、池上鄉、延平鄉、海端鄉"
  },
  {
    "斷層名稱": "池上斷層",
    "r": "5",
    "SDS": "1.06",
    "SD1": "0.65",
    "SMS": "1.18",
    "SM1": "0.76",
    "對應鄉鎮": "[花蓮縣] 花蓮市、鳳林鎮、玉里鎮、新城鄉、吉安鄉、壽豐鄉、光復鄉、豐濱鄉、瑞穗鄉、富里鄉、秀林鄉、萬榮鄉、卓溪鄉 [臺東縣] 臺東市、成功鎮、關山鎮、卑南鄉、東河鄉、長濱鄉、鹿野鄉、池上鄉、延平鄉、海端鄉"
  },
  {
    "斷層名稱": "池上斷層",
    "r": "7",
    "SDS": "1.01",
    "SD1": "0.61",
    "SMS": "1.09",
    "SM1": "0.7",
    "對應鄉鎮": "[花蓮縣] 花蓮市、鳳林鎮、玉里鎮、新城鄉、吉安鄉、壽豐鄉、光復鄉、豐濱鄉、瑞穗鄉、富里鄉、秀林鄉、萬榮鄉、卓溪鄉 [臺東縣] 臺東市、成功鎮、關山鎮、卑南鄉、東河鄉、長濱鄉、鹿野鄉、池上鄉、延平鄉、海端鄉"
  },
  {
    "斷層名稱": "池上斷層",
    "r": "9",
    "SDS": "0.94",
    "SD1": "0.56",
    "SMS": "1.04",
    "SM1": "0.66",
    "對應鄉鎮": "[花蓮縣] 花蓮市、鳳林鎮、玉里鎮、新城鄉、吉安鄉、壽豐鄉、光復鄉、豐濱鄉、瑞穗鄉、富里鄉、秀林鄉、萬榮鄉、卓溪鄉 [臺東縣] 臺東市、成功鎮、關山鎮、卑南鄉、東河鄉、長濱鄉、鹿野鄉、池上鄉、延平鄉、海端鄉"
  },
  {
    "斷層名稱": "池上斷層",
    "r": "11",
    "SDS": "0.87",
    "SD1": "0.51",
    "SMS": "1.01",
    "SM1": "0.61",
    "對應鄉鎮": "[花蓮縣] 花蓮市、鳳林鎮、玉里鎮、新城鄉、吉安鄉、壽豐鄉、光復鄉、豐濱鄉、瑞穗鄉、富里鄉、秀林鄉、萬榮鄉、卓溪鄉 [臺東縣] 臺東市、成功鎮、關山鎮、卑南鄉、東河鄉、長濱鄉、鹿野鄉、池上鄉、延平鄉、海端鄉"
  },
  {
    "斷層名稱": "池上斷層",
    "r": "13",
    "SDS": "0.8",
    "SD1": "0.45",
    "SMS": "1",
    "SM1": "0.55",
    "對應鄉鎮": "[花蓮縣] 花蓮市、鳳林鎮、玉里鎮、新城鄉、吉安鄉、壽豐鄉、光復鄉、豐濱鄉、瑞穗鄉、富里鄉、秀林鄉、萬榮鄉、卓溪鄉 [臺東縣] 臺東市、成功鎮、關山鎮、卑南鄉、東河鄉、長濱鄉、鹿野鄉、池上鄉、延平鄉、海端鄉"
  },
  {
    "斷層名稱": "池上斷層",
    "r": ">=14",
    "SDS": "0.8",
    "SD1": "0.45",
    "SMS": "1",
    "SM1": "0.55",
    "對應鄉鎮": "[花蓮縣] 花蓮市、鳳林鎮、玉里鎮、新城鄉、吉安鄉、壽豐鄉、光復鄉、豐濱鄉、瑞穗鄉、富里鄉、秀林鄉、萬榮鄉、卓溪鄉 [臺東縣] 臺東市、成功鎮、關山鎮、卑南鄉、東河鄉、長濱鄉、鹿野鄉、池上鄉、延平鄉、海端鄉"
  },
  {
    "斷層名稱": "鹿野斷層",
    "r": "<=1",
    "SDS": "1.14",
    "SD1": "0.71",
    "SMS": "1.32",
    "SM1": "0.87",
    "對應鄉鎮": "[花蓮縣] 花蓮市、鳳林鎮、玉里鎮、新城鄉、吉安鄉、壽豐鄉、光復鄉、豐濱鄉、瑞穗鄉、富里鄉、秀林鄉、萬榮鄉、卓溪鄉 [臺東縣] 臺東市、成功鎮、關山鎮、卑南鄉、東河鄉、長濱鄉、鹿野鄉、池上鄉、延平鄉、海端鄉"
  },
  {
    "斷層名稱": "鹿野斷層",
    "r": "3",
    "SDS": "1.1",
    "SD1": "0.69",
    "SMS": "1.27",
    "SM1": "0.83",
    "對應鄉鎮": "[花蓮縣] 花蓮市、鳳林鎮、玉里鎮、新城鄉、吉安鄉、壽豐鄉、光復鄉、豐濱鄉、瑞穗鄉、富里鄉、秀林鄉、萬榮鄉、卓溪鄉 [臺東縣] 臺東市、成功鎮、關山鎮、卑南鄉、東河鄉、長濱鄉、鹿野鄉、池上鄉、延平鄉、海端鄉"
  },
  {
    "斷層名稱": "鹿野斷層",
    "r": "5",
    "SDS": "1.06",
    "SD1": "0.65",
    "SMS": "1.18",
    "SM1": "0.76",
    "對應鄉鎮": "[花蓮縣] 花蓮市、鳳林鎮、玉里鎮、新城鄉、吉安鄉、壽豐鄉、光復鄉、豐濱鄉、瑞穗鄉、富里鄉、秀林鄉、萬榮鄉、卓溪鄉 [臺東縣] 臺東市、成功鎮、關山鎮、卑南鄉、東河鄉、長濱鄉、鹿野鄉、池上鄉、延平鄉、海端鄉"
  },
  {
    "斷層名稱": "鹿野斷層",
    "r": "7",
    "SDS": "1.01",
    "SD1": "0.61",
    "SMS": "1.09",
    "SM1": "0.7",
    "對應鄉鎮": "[花蓮縣] 花蓮市、鳳林鎮、玉里鎮、新城鄉、吉安鄉、壽豐鄉、光復鄉、豐濱鄉、瑞穗鄉、富里鄉、秀林鄉、萬榮鄉、卓溪鄉 [臺東縣] 臺東市、成功鎮、關山鎮、卑南鄉、東河鄉、長濱鄉、鹿野鄉、池上鄉、延平鄉、海端鄉"
  },
  {
    "斷層名稱": "鹿野斷層",
    "r": "9",
    "SDS": "0.94",
    "SD1": "0.56",
    "SMS": "1.04",
    "SM1": "0.66",
    "對應鄉鎮": "[花蓮縣] 花蓮市、鳳林鎮、玉里鎮、新城鄉、吉安鄉、壽豐鄉、光復鄉、豐濱鄉、瑞穗鄉、富里鄉、秀林鄉、萬榮鄉、卓溪鄉 [臺東縣] 臺東市、成功鎮、關山鎮、卑南鄉、東河鄉、長濱鄉、鹿野鄉、池上鄉、延平鄉、海端鄉"
  },
  {
    "斷層名稱": "鹿野斷層",
    "r": "11",
    "SDS": "0.87",
    "SD1": "0.51",
    "SMS": "1.01",
    "SM1": "0.61",
    "對應鄉鎮": "[花蓮縣] 花蓮市、鳳林鎮、玉里鎮、新城鄉、吉安鄉、壽豐鄉、光復鄉、豐濱鄉、瑞穗鄉、富里鄉、秀林鄉、萬榮鄉、卓溪鄉 [臺東縣] 臺東市、成功鎮、關山鎮、卑南鄉、東河鄉、長濱鄉、鹿野鄉、池上鄉、延平鄉、海端鄉"
  },
  {
    "斷層名稱": "鹿野斷層",
    "r": "13",
    "SDS": "0.8",
    "SD1": "0.45",
    "SMS": "1",
    "SM1": "0.55",
    "對應鄉鎮": "[花蓮縣] 花蓮市、鳳林鎮、玉里鎮、新城鄉、吉安鄉、壽豐鄉、光復鄉、豐濱鄉、瑞穗鄉、富里鄉、秀林鄉、萬榮鄉、卓溪鄉 [臺東縣] 臺東市、成功鎮、關山鎮、卑南鄉、東河鄉、長濱鄉、鹿野鄉、池上鄉、延平鄉、海端鄉"
  },
  {
    "斷層名稱": "鹿野斷層",
    "r": ">=14",
    "SDS": "0.8",
    "SD1": "0.45",
    "SMS": "1",
    "SM1": "0.55",
    "對應鄉鎮": "[花蓮縣] 花蓮市、鳳林鎮、玉里鎮、新城鄉、吉安鄉、壽豐鄉、光復鄉、豐濱鄉、瑞穗鄉、富里鄉、秀林鄉、萬榮鄉、卓溪鄉 [臺東縣] 臺東市、成功鎮、關山鎮、卑南鄉、東河鄉、長濱鄉、鹿野鄉、池上鄉、延平鄉、海端鄉"
  },
  {
    "斷層名稱": "利吉斷層",
    "r": "<=1",
    "SDS": "1.14",
    "SD1": "0.71",
    "SMS": "1.32",
    "SM1": "0.87",
    "對應鄉鎮": "[花蓮縣] 花蓮市、鳳林鎮、玉里鎮、新城鄉、吉安鄉、壽豐鄉、光復鄉、豐濱鄉、瑞穗鄉、富里鄉、秀林鄉、萬榮鄉、卓溪鄉 [臺東縣] 臺東市、成功鎮、關山鎮、卑南鄉、東河鄉、長濱鄉、鹿野鄉、池上鄉、延平鄉、海端鄉"
  },
  {
    "斷層名稱": "利吉斷層",
    "r": "3",
    "SDS": "1.1",
    "SD1": "0.69",
    "SMS": "1.27",
    "SM1": "0.83",
    "對應鄉鎮": "[花蓮縣] 花蓮市、鳳林鎮、玉里鎮、新城鄉、吉安鄉、壽豐鄉、光復鄉、豐濱鄉、瑞穗鄉、富里鄉、秀林鄉、萬榮鄉、卓溪鄉 [臺東縣] 臺東市、成功鎮、關山鎮、卑南鄉、東河鄉、長濱鄉、鹿野鄉、池上鄉、延平鄉、海端鄉"
  },
  {
    "斷層名稱": "利吉斷層",
    "r": "5",
    "SDS": "1.06",
    "SD1": "0.65",
    "SMS": "1.18",
    "SM1": "0.76",
    "對應鄉鎮": "[花蓮縣] 花蓮市、鳳林鎮、玉里鎮、新城鄉、吉安鄉、壽豐鄉、光復鄉、豐濱鄉、瑞穗鄉、富里鄉、秀林鄉、萬榮鄉、卓溪鄉 [臺東縣] 臺東市、成功鎮、關山鎮、卑南鄉、東河鄉、長濱鄉、鹿野鄉、池上鄉、延平鄉、海端鄉"
  },
  {
    "斷層名稱": "利吉斷層",
    "r": "7",
    "SDS": "1.01",
    "SD1": "0.61",
    "SMS": "1.09",
    "SM1": "0.7",
    "對應鄉鎮": "[花蓮縣] 花蓮市、鳳林鎮、玉里鎮、新城鄉、吉安鄉、壽豐鄉、光復鄉、豐濱鄉、瑞穗鄉、富里鄉、秀林鄉、萬榮鄉、卓溪鄉 [臺東縣] 臺東市、成功鎮、關山鎮、卑南鄉、東河鄉、長濱鄉、鹿野鄉、池上鄉、延平鄉、海端鄉"
  },
  {
    "斷層名稱": "利吉斷層",
    "r": "9",
    "SDS": "0.94",
    "SD1": "0.56",
    "SMS": "1.04",
    "SM1": "0.66",
    "對應鄉鎮": "[花蓮縣] 花蓮市、鳳林鎮、玉里鎮、新城鄉、吉安鄉、壽豐鄉、光復鄉、豐濱鄉、瑞穗鄉、富里鄉、秀林鄉、萬榮鄉、卓溪鄉 [臺東縣] 臺東市、成功鎮、關山鎮、卑南鄉、東河鄉、長濱鄉、鹿野鄉、池上鄉、延平鄉、海端鄉"
  },
  {
    "斷層名稱": "利吉斷層",
    "r": "11",
    "SDS": "0.87",
    "SD1": "0.51",
    "SMS": "1.01",
    "SM1": "0.61",
    "對應鄉鎮": "[花蓮縣] 花蓮市、鳳林鎮、玉里鎮、新城鄉、吉安鄉、壽豐鄉、光復鄉、豐濱鄉、瑞穗鄉、富里鄉、秀林鄉、萬榮鄉、卓溪鄉 [臺東縣] 臺東市、成功鎮、關山鎮、卑南鄉、東河鄉、長濱鄉、鹿野鄉、池上鄉、延平鄉、海端鄉"
  },
  {
    "斷層名稱": "利吉斷層",
    "r": "13",
    "SDS": "0.8",
    "SD1": "0.45",
    "SMS": "1",
    "SM1": "0.55",
    "對應鄉鎮": "[花蓮縣] 花蓮市、鳳林鎮、玉里鎮、新城鄉、吉安鄉、壽豐鄉、光復鄉、豐濱鄉、瑞穗鄉、富里鄉、秀林鄉、萬榮鄉、卓溪鄉 [臺東縣] 臺東市、成功鎮、關山鎮、卑南鄉、東河鄉、長濱鄉、鹿野鄉、池上鄉、延平鄉、海端鄉"
  },
  {
    "斷層名稱": "利吉斷層",
    "r": ">=14",
    "SDS": "0.8",
    "SD1": "0.45",
    "SMS": "1",
    "SM1": "0.55",
    "對應鄉鎮": "[花蓮縣] 花蓮市、鳳林鎮、玉里鎮、新城鄉、吉安鄉、壽豐鄉、光復鄉、豐濱鄉、瑞穗鄉、富里鄉、秀林鄉、萬榮鄉、卓溪鄉 [臺東縣] 臺東市、成功鎮、關山鎮、卑南鄉、東河鄉、長濱鄉、鹿野鄉、池上鄉、延平鄉、海端鄉"
  }
]
